{"scenario": 2, "period": 8, "subperiod": 5, "num_orders": 86, "orders": [{"order_id": 0, "num_orderlines": 4, "total_weight": 2.396, "orderlines": [{"item": 99, "quantity": 1, "location": 2497, "weight": 0.966}, {"item": 732, "quantity": 1, "location": 4666, "weight": 0.2}, {"item": 113, "quantity": 1, "location": 358, "weight": 0.621}, {"item": 15, "quantity": 2, "location": 1070, "weight": 0.609}]}, {"order_id": 1, "num_orderlines": 9, "total_weight": 7.888, "orderlines": [{"item": 46, "quantity": 1, "location": 2864, "weight": 0.449}, {"item": 63, "quantity": 1, "location": 319, "weight": 0.788}, {"item": 104, "quantity": 2, "location": 3235, "weight": 1.602}, {"item": 850, "quantity": 2, "location": 3583, "weight": 0.521}, {"item": 540, "quantity": 1, "location": 1736, "weight": 0.99}, {"item": 235, "quantity": 2, "location": 332, "weight": 1.648}, {"item": 361, "quantity": 2, "location": 2838, "weight": 0.416}, {"item": 599, "quantity": 2, "location": 2435, "weight": 1.317}, {"item": 17, "quantity": 1, "location": 323, "weight": 0.157}]}, {"order_id": 2, "num_orderlines": 9, "total_weight": 5.718, "orderlines": [{"item": 787, "quantity": 1, "location": 3924, "weight": 0.387}, {"item": 142, "quantity": 2, "location": 1069, "weight": 1.888}, {"item": 747, "quantity": 1, "location": 2834, "weight": 0.488}, {"item": 162, "quantity": 1, "location": 2511, "weight": 0.307}, {"item": 445, "quantity": 1, "location": 4267, "weight": 0.739}, {"item": 289, "quantity": 1, "location": 1797, "weight": 0.192}, {"item": 195, "quantity": 2, "location": 1078, "weight": 0.523}, {"item": 36, "quantity": 1, "location": 2500, "weight": 0.217}, {"item": 5, "quantity": 1, "location": 1076, "weight": 0.978}]}, {"order_id": 3, "num_orderlines": 8, "total_weight": 6.244, "orderlines": [{"item": 380, "quantity": 1, "location": 4631, "weight": 0.598}, {"item": 136, "quantity": 1, "location": 705, "weight": 0.963}, {"item": 111, "quantity": 2, "location": 2126, "weight": 0.564}, {"item": 293, "quantity": 1, "location": 1790, "weight": 0.189}, {"item": 31, "quantity": 2, "location": 1403, "weight": 1.942}, {"item": 32, "quantity": 2, "location": 701, "weight": 0.786}, {"item": 17, "quantity": 1, "location": 323, "weight": 0.157}, {"item": 550, "quantity": 2, "location": 971, "weight": 1.045}]}, {"order_id": 4, "num_orderlines": 10, "total_weight": 9.263, "orderlines": [{"item": 49, "quantity": 2, "location": 1411, "weight": 0.452}, {"item": 566, "quantity": 2, "location": 1029, "weight": 1.573}, {"item": 271, "quantity": 2, "location": 1075, "weight": 0.514}, {"item": 306, "quantity": 2, "location": 4642, "weight": 0.893}, {"item": 303, "quantity": 2, "location": 987, "weight": 1.126}, {"item": 94, "quantity": 1, "location": 1051, "weight": 0.371}, {"item": 95, "quantity": 2, "location": 1764, "weight": 1.335}, {"item": 703, "quantity": 2, "location": 4625, "weight": 1.774}, {"item": 329, "quantity": 1, "location": 604, "weight": 0.359}, {"item": 279, "quantity": 1, "location": 334, "weight": 0.866}]}, {"order_id": 5, "num_orderlines": 3, "total_weight": 3.375, "orderlines": [{"item": 148, "quantity": 2, "location": 344, "weight": 0.99}, {"item": 439, "quantity": 1, "location": 4657, "weight": 0.667}, {"item": 294, "quantity": 2, "location": 353, "weight": 1.718}]}, {"order_id": 6, "num_orderlines": 6, "total_weight": 4.955, "orderlines": [{"item": 10, "quantity": 2, "location": 2148, "weight": 0.867}, {"item": 169, "quantity": 2, "location": 1432, "weight": 1.915}, {"item": 163, "quantity": 1, "location": 670, "weight": 0.134}, {"item": 346, "quantity": 1, "location": 607, "weight": 0.951}, {"item": 373, "quantity": 2, "location": 4263, "weight": 0.766}, {"item": 680, "quantity": 2, "location": 1372, "weight": 0.321}]}, {"order_id": 7, "num_orderlines": 9, "total_weight": 8.647, "orderlines": [{"item": 52, "quantity": 1, "location": 1397, "weight": 0.808}, {"item": 278, "quantity": 1, "location": 1032, "weight": 0.887}, {"item": 106, "quantity": 2, "location": 1035, "weight": 1.009}, {"item": 852, "quantity": 2, "location": 2119, "weight": 1.746}, {"item": 410, "quantity": 2, "location": 7185, "weight": 1.398}, {"item": 687, "quantity": 1, "location": 3948, "weight": 0.963}, {"item": 138, "quantity": 1, "location": 3230, "weight": 0.804}, {"item": 88, "quantity": 1, "location": 687, "weight": 0.245}, {"item": 6, "quantity": 1, "location": 1393, "weight": 0.785}]}, {"order_id": 8, "num_orderlines": 4, "total_weight": 3.308, "orderlines": [{"item": 353, "quantity": 2, "location": 1697, "weight": 1.23}, {"item": 724, "quantity": 1, "location": 4624, "weight": 0.193}, {"item": 116, "quantity": 1, "location": 3597, "weight": 0.783}, {"item": 89, "quantity": 2, "location": 1791, "weight": 1.102}]}, {"order_id": 9, "num_orderlines": 2, "total_weight": 1.354, "orderlines": [{"item": 498, "quantity": 2, "location": 6455, "weight": 0.849}, {"item": 9, "quantity": 1, "location": 339, "weight": 0.505}]}, {"order_id": 10, "num_orderlines": 6, "total_weight": 5.619, "orderlines": [{"item": 491, "quantity": 2, "location": 625, "weight": 1.366}, {"item": 344, "quantity": 1, "location": 3568, "weight": 0.804}, {"item": 167, "quantity": 1, "location": 2145, "weight": 0.827}, {"item": 31, "quantity": 2, "location": 1403, "weight": 1.942}, {"item": 4, "quantity": 2, "location": 680, "weight": 0.37}, {"item": 242, "quantity": 1, "location": 1392, "weight": 0.309}]}, {"order_id": 11, "num_orderlines": 3, "total_weight": 3.654, "orderlines": [{"item": 0, "quantity": 2, "location": 716, "weight": 1.593}, {"item": 716, "quantity": 1, "location": 2824, "weight": 0.606}, {"item": 3, "quantity": 2, "location": 700, "weight": 1.455}]}, {"order_id": 12, "num_orderlines": 5, "total_weight": 4.852, "orderlines": [{"item": 492, "quantity": 1, "location": 6119, "weight": 0.687}, {"item": 236, "quantity": 1, "location": 1773, "weight": 0.521}, {"item": 12, "quantity": 2, "location": 2506, "weight": 1.359}, {"item": 0, "quantity": 2, "location": 716, "weight": 1.593}, {"item": 819, "quantity": 2, "location": 1011, "weight": 0.692}]}, {"order_id": 13, "num_orderlines": 8, "total_weight": 6.427, "orderlines": [{"item": 85, "quantity": 2, "location": 663, "weight": 0.362}, {"item": 1, "quantity": 2, "location": 313, "weight": 0.99}, {"item": 146, "quantity": 2, "location": 679, "weight": 0.797}, {"item": 208, "quantity": 2, "location": 2132, "weight": 0.419}, {"item": 199, "quantity": 1, "location": 1399, "weight": 0.379}, {"item": 200, "quantity": 2, "location": 2870, "weight": 1.599}, {"item": 72, "quantity": 2, "location": 1415, "weight": 1.736}, {"item": 286, "quantity": 1, "location": 1424, "weight": 0.144}]}, {"order_id": 14, "num_orderlines": 4, "total_weight": 3.968, "orderlines": [{"item": 638, "quantity": 2, "location": 3543, "weight": 1.593}, {"item": 712, "quantity": 2, "location": 6477, "weight": 1.666}, {"item": 217, "quantity": 1, "location": 320, "weight": 0.211}, {"item": 797, "quantity": 2, "location": 5020, "weight": 0.498}]}, {"order_id": 15, "num_orderlines": 5, "total_weight": 3.239, "orderlines": [{"item": 83, "quantity": 2, "location": 2858, "weight": 0.501}, {"item": 149, "quantity": 1, "location": 2138, "weight": 0.119}, {"item": 689, "quantity": 1, "location": 1385, "weight": 0.587}, {"item": 79, "quantity": 2, "location": 1793, "weight": 1.611}, {"item": 192, "quantity": 2, "location": 2133, "weight": 0.421}]}, {"order_id": 16, "num_orderlines": 10, "total_weight": 10.599, "orderlines": [{"item": 379, "quantity": 1, "location": 1001, "weight": 0.757}, {"item": 0, "quantity": 2, "location": 716, "weight": 1.593}, {"item": 105, "quantity": 1, "location": 2507, "weight": 0.745}, {"item": 81, "quantity": 2, "location": 3589, "weight": 0.931}, {"item": 222, "quantity": 2, "location": 710, "weight": 1.393}, {"item": 56, "quantity": 1, "location": 2869, "weight": 0.513}, {"item": 101, "quantity": 1, "location": 1417, "weight": 0.73}, {"item": 3, "quantity": 2, "location": 700, "weight": 1.455}, {"item": 824, "quantity": 1, "location": 2079, "weight": 0.853}, {"item": 626, "quantity": 2, "location": 3171, "weight": 1.629}]}, {"order_id": 17, "num_orderlines": 10, "total_weight": 9.276, "orderlines": [{"item": 759, "quantity": 1, "location": 5030, "weight": 0.515}, {"item": 152, "quantity": 2, "location": 1036, "weight": 0.452}, {"item": 11, "quantity": 2, "location": 307, "weight": 1.868}, {"item": 0, "quantity": 2, "location": 716, "weight": 1.593}, {"item": 375, "quantity": 1, "location": 3954, "weight": 0.233}, {"item": 92, "quantity": 2, "location": 1060, "weight": 1.003}, {"item": 182, "quantity": 2, "location": 1039, "weight": 1.134}, {"item": 518, "quantity": 1, "location": 2819, "weight": 0.113}, {"item": 155, "quantity": 2, "location": 2514, "weight": 1.41}, {"item": 231, "quantity": 2, "location": 697, "weight": 0.954}]}, {"order_id": 18, "num_orderlines": 2, "total_weight": 1.042, "orderlines": [{"item": 374, "quantity": 1, "location": 288, "weight": 0.242}, {"item": 620, "quantity": 1, "location": 2848, "weight": 0.8}]}, {"order_id": 19, "num_orderlines": 8, "total_weight": 7.297, "orderlines": [{"item": 822, "quantity": 2, "location": 964, "weight": 0.731}, {"item": 4, "quantity": 1, "location": 680, "weight": 0.185}, {"item": 77, "quantity": 2, "location": 702, "weight": 1.391}, {"item": 240, "quantity": 1, "location": 348, "weight": 0.847}, {"item": 131, "quantity": 1, "location": 2152, "weight": 0.933}, {"item": 606, "quantity": 2, "location": 4635, "weight": 1.76}, {"item": 41, "quantity": 1, "location": 2867, "weight": 0.849}, {"item": 78, "quantity": 1, "location": 681, "weight": 0.601}]}, {"order_id": 20, "num_orderlines": 5, "total_weight": 3.081, "orderlines": [{"item": 273, "quantity": 2, "location": 2144, "weight": 1.264}, {"item": 472, "quantity": 2, "location": 633, "weight": 0.415}, {"item": 265, "quantity": 1, "location": 1792, "weight": 0.249}, {"item": 300, "quantity": 1, "location": 2791, "weight": 0.801}, {"item": 122, "quantity": 2, "location": 1044, "weight": 0.352}]}, {"order_id": 21, "num_orderlines": 9, "total_weight": 6.255, "orderlines": [{"item": 280, "quantity": 2, "location": 1784, "weight": 0.278}, {"item": 251, "quantity": 1, "location": 306, "weight": 0.881}, {"item": 469, "quantity": 1, "location": 1386, "weight": 0.557}, {"item": 159, "quantity": 1, "location": 1783, "weight": 0.792}, {"item": 799, "quantity": 2, "location": 5756, "weight": 1.475}, {"item": 198, "quantity": 2, "location": 1767, "weight": 0.554}, {"item": 10, "quantity": 1, "location": 2148, "weight": 0.434}, {"item": 496, "quantity": 1, "location": 4997, "weight": 0.488}, {"item": 0, "quantity": 1, "location": 716, "weight": 0.797}]}, {"order_id": 22, "num_orderlines": 7, "total_weight": 7.407, "orderlines": [{"item": 115, "quantity": 2, "location": 1033, "weight": 1.742}, {"item": 0, "quantity": 2, "location": 716, "weight": 1.593}, {"item": 43, "quantity": 1, "location": 689, "weight": 0.381}, {"item": 33, "quantity": 2, "location": 3232, "weight": 0.867}, {"item": 151, "quantity": 2, "location": 1043, "weight": 1.813}, {"item": 181, "quantity": 1, "location": 1063, "weight": 0.904}, {"item": 51, "quantity": 1, "location": 2135, "weight": 0.107}]}, {"order_id": 23, "num_orderlines": 1, "total_weight": 0.128, "orderlines": [{"item": 68, "quantity": 1, "location": 1406, "weight": 0.128}]}, {"order_id": 24, "num_orderlines": 10, "total_weight": 7.757, "orderlines": [{"item": 0, "quantity": 1, "location": 716, "weight": 0.797}, {"item": 90, "quantity": 2, "location": 1074, "weight": 0.474}, {"item": 154, "quantity": 1, "location": 1431, "weight": 0.198}, {"item": 698, "quantity": 1, "location": 6462, "weight": 0.688}, {"item": 42, "quantity": 1, "location": 1774, "weight": 0.73}, {"item": 249, "quantity": 1, "location": 661, "weight": 0.483}, {"item": 180, "quantity": 2, "location": 359, "weight": 1.803}, {"item": 214, "quantity": 2, "location": 1394, "weight": 1.488}, {"item": 134, "quantity": 1, "location": 2155, "weight": 0.632}, {"item": 470, "quantity": 1, "location": 3165, "weight": 0.464}]}, {"order_id": 25, "num_orderlines": 10, "total_weight": 9.444, "orderlines": [{"item": 6, "quantity": 1, "location": 1393, "weight": 0.785}, {"item": 2, "quantity": 2, "location": 340, "weight": 1.745}, {"item": 110, "quantity": 1, "location": 2504, "weight": 0.51}, {"item": 9, "quantity": 2, "location": 339, "weight": 1.011}, {"item": 130, "quantity": 1, "location": 2868, "weight": 0.254}, {"item": 297, "quantity": 2, "location": 1778, "weight": 1.644}, {"item": 14, "quantity": 2, "location": 693, "weight": 0.998}, {"item": 421, "quantity": 2, "location": 1009, "weight": 0.265}, {"item": 241, "quantity": 2, "location": 1777, "weight": 1.634}, {"item": 65, "quantity": 1, "location": 2862, "weight": 0.598}]}, {"order_id": 26, "num_orderlines": 8, "total_weight": 8.162, "orderlines": [{"item": 150, "quantity": 2, "location": 1430, "weight": 1.687}, {"item": 178, "quantity": 1, "location": 1396, "weight": 0.902}, {"item": 275, "quantity": 1, "location": 3236, "weight": 0.454}, {"item": 55, "quantity": 2, "location": 1782, "weight": 1.605}, {"item": 719, "quantity": 1, "location": 3162, "weight": 0.96}, {"item": 0, "quantity": 2, "location": 716, "weight": 1.593}, {"item": 552, "quantity": 2, "location": 3925, "weight": 0.526}, {"item": 10, "quantity": 1, "location": 2148, "weight": 0.434}]}, {"order_id": 27, "num_orderlines": 7, "total_weight": 6.861, "orderlines": [{"item": 0, "quantity": 2, "location": 716, "weight": 1.593}, {"item": 602, "quantity": 2, "location": 4630, "weight": 1.826}, {"item": 243, "quantity": 1, "location": 2128, "weight": 0.578}, {"item": 307, "quantity": 2, "location": 4994, "weight": 1.351}, {"item": 582, "quantity": 2, "location": 4995, "weight": 0.389}, {"item": 592, "quantity": 1, "location": 265, "weight": 0.377}, {"item": 117, "quantity": 1, "location": 2142, "weight": 0.748}]}, {"order_id": 28, "num_orderlines": 3, "total_weight": 1.942, "orderlines": [{"item": 39, "quantity": 1, "location": 1073, "weight": 0.703}, {"item": 93, "quantity": 1, "location": 2876, "weight": 0.443}, {"item": 0, "quantity": 1, "location": 716, "weight": 0.797}]}, {"order_id": 29, "num_orderlines": 5, "total_weight": 6.51, "orderlines": [{"item": 576, "quantity": 2, "location": 4996, "weight": 1.837}, {"item": 114, "quantity": 1, "location": 684, "weight": 0.259}, {"item": 5, "quantity": 2, "location": 1076, "weight": 1.956}, {"item": 0, "quantity": 2, "location": 716, "weight": 1.593}, {"item": 773, "quantity": 1, "location": 2452, "weight": 0.865}]}, {"order_id": 30, "num_orderlines": 3, "total_weight": 2.09, "orderlines": [{"item": 70, "quantity": 1, "location": 1429, "weight": 0.293}, {"item": 13, "quantity": 2, "location": 1795, "weight": 1.681}, {"item": 682, "quantity": 1, "location": 3160, "weight": 0.116}]}, {"order_id": 31, "num_orderlines": 1, "total_weight": 0.671, "orderlines": [{"item": 478, "quantity": 1, "location": 6465, "weight": 0.671}]}, {"order_id": 32, "num_orderlines": 8, "total_weight": 5.463, "orderlines": [{"item": 459, "quantity": 1, "location": 3959, "weight": 0.673}, {"item": 233, "quantity": 2, "location": 314, "weight": 1.273}, {"item": 395, "quantity": 1, "location": 1332, "weight": 0.509}, {"item": 203, "quantity": 1, "location": 2516, "weight": 0.23}, {"item": 563, "quantity": 2, "location": 4280, "weight": 1.348}, {"item": 559, "quantity": 1, "location": 6467, "weight": 0.544}, {"item": 619, "quantity": 1, "location": 3180, "weight": 0.137}, {"item": 112, "quantity": 2, "location": 321, "weight": 0.751}]}, {"order_id": 33, "num_orderlines": 1, "total_weight": 0.198, "orderlines": [{"item": 239, "quantity": 1, "location": 3593, "weight": 0.198}]}, {"order_id": 34, "num_orderlines": 7, "total_weight": 4.954, "orderlines": [{"item": 188, "quantity": 1, "location": 1048, "weight": 0.772}, {"item": 175, "quantity": 2, "location": 355, "weight": 0.281}, {"item": 600, "quantity": 1, "location": 3562, "weight": 0.53}, {"item": 133, "quantity": 1, "location": 322, "weight": 0.412}, {"item": 0, "quantity": 1, "location": 716, "weight": 0.797}, {"item": 791, "quantity": 1, "location": 5393, "weight": 0.473}, {"item": 18, "quantity": 2, "location": 2498, "weight": 1.69}]}, {"order_id": 35, "num_orderlines": 3, "total_weight": 1.53, "orderlines": [{"item": 589, "quantity": 2, "location": 277, "weight": 0.245}, {"item": 118, "quantity": 1, "location": 3594, "weight": 0.489}, {"item": 0, "quantity": 1, "location": 716, "weight": 0.797}]}, {"order_id": 36, "num_orderlines": 1, "total_weight": 0.428, "orderlines": [{"item": 814, "quantity": 2, "location": 2097, "weight": 0.428}]}, {"order_id": 37, "num_orderlines": 10, "total_weight": 6.251, "orderlines": [{"item": 15, "quantity": 1, "location": 1070, "weight": 0.304}, {"item": 71, "quantity": 1, "location": 1776, "weight": 0.468}, {"item": 634, "quantity": 1, "location": 1723, "weight": 0.144}, {"item": 24, "quantity": 2, "location": 351, "weight": 1.601}, {"item": 137, "quantity": 1, "location": 1438, "weight": 0.534}, {"item": 61, "quantity": 1, "location": 333, "weight": 0.524}, {"item": 135, "quantity": 1, "location": 354, "weight": 0.12}, {"item": 121, "quantity": 2, "location": 330, "weight": 1.37}, {"item": 13, "quantity": 1, "location": 1795, "weight": 0.841}, {"item": 107, "quantity": 1, "location": 678, "weight": 0.345}]}, {"order_id": 38, "num_orderlines": 1, "total_weight": 0.99, "orderlines": [{"item": 1, "quantity": 2, "location": 313, "weight": 0.99}]}, {"order_id": 39, "num_orderlines": 3, "total_weight": 2.708, "orderlines": [{"item": 813, "quantity": 2, "location": 1384, "weight": 1.252}, {"item": 352, "quantity": 2, "location": 5016, "weight": 1.217}, {"item": 28, "quantity": 1, "location": 1067, "weight": 0.239}]}, {"order_id": 40, "num_orderlines": 8, "total_weight": 7.037, "orderlines": [{"item": 500, "quantity": 2, "location": 2434, "weight": 1.526}, {"item": 515, "quantity": 1, "location": 3174, "weight": 0.256}, {"item": 801, "quantity": 2, "location": 2788, "weight": 0.771}, {"item": 260, "quantity": 1, "location": 2129, "weight": 0.232}, {"item": 364, "quantity": 2, "location": 2468, "weight": 1.384}, {"item": 35, "quantity": 2, "location": 301, "weight": 0.541}, {"item": 2, "quantity": 2, "location": 340, "weight": 1.745}, {"item": 854, "quantity": 2, "location": 3209, "weight": 0.582}]}, {"order_id": 41, "num_orderlines": 6, "total_weight": 6.37, "orderlines": [{"item": 66, "quantity": 2, "location": 3599, "weight": 1.207}, {"item": 390, "quantity": 2, "location": 1002, "weight": 1.347}, {"item": 584, "quantity": 2, "location": 5391, "weight": 1.851}, {"item": 185, "quantity": 1, "location": 709, "weight": 0.696}, {"item": 616, "quantity": 1, "location": 1010, "weight": 0.775}, {"item": 1, "quantity": 1, "location": 313, "weight": 0.495}]}, {"order_id": 42, "num_orderlines": 5, "total_weight": 2.279, "orderlines": [{"item": 535, "quantity": 2, "location": 5377, "weight": 0.576}, {"item": 50, "quantity": 1, "location": 2137, "weight": 0.28}, {"item": 212, "quantity": 1, "location": 1055, "weight": 0.28}, {"item": 25, "quantity": 1, "location": 1041, "weight": 0.275}, {"item": 165, "quantity": 2, "location": 1794, "weight": 0.868}]}, {"order_id": 43, "num_orderlines": 10, "total_weight": 6.93, "orderlines": [{"item": 156, "quantity": 1, "location": 1414, "weight": 0.353}, {"item": 823, "quantity": 1, "location": 1363, "weight": 0.697}, {"item": 11, "quantity": 2, "location": 307, "weight": 1.868}, {"item": 97, "quantity": 1, "location": 2877, "weight": 0.179}, {"item": 23, "quantity": 2, "location": 1439, "weight": 1.808}, {"item": 270, "quantity": 1, "location": 1769, "weight": 0.15}, {"item": 22, "quantity": 1, "location": 1412, "weight": 0.974}, {"item": 221, "quantity": 1, "location": 2866, "weight": 0.54}, {"item": 108, "quantity": 1, "location": 2149, "weight": 0.187}, {"item": 139, "quantity": 1, "location": 1409, "weight": 0.174}]}, {"order_id": 44, "num_orderlines": 8, "total_weight": 9.394, "orderlines": [{"item": 86, "quantity": 2, "location": 1789, "weight": 1.5}, {"item": 458, "quantity": 2, "location": 4992, "weight": 1.611}, {"item": 145, "quantity": 1, "location": 1765, "weight": 0.34}, {"item": 19, "quantity": 2, "location": 1787, "weight": 1.337}, {"item": 168, "quantity": 2, "location": 311, "weight": 0.771}, {"item": 561, "quantity": 2, "location": 5743, "weight": 0.639}, {"item": 530, "quantity": 2, "location": 5367, "weight": 1.438}, {"item": 639, "quantity": 2, "location": 3184, "weight": 1.758}]}, {"order_id": 45, "num_orderlines": 3, "total_weight": 2.574, "orderlines": [{"item": 64, "quantity": 2, "location": 2502, "weight": 1.342}, {"item": 211, "quantity": 1, "location": 1402, "weight": 0.623}, {"item": 62, "quantity": 1, "location": 1779, "weight": 0.609}]}, {"order_id": 46, "num_orderlines": 10, "total_weight": 8.261, "orderlines": [{"item": 84, "quantity": 2, "location": 1766, "weight": 0.241}, {"item": 3, "quantity": 2, "location": 700, "weight": 1.455}, {"item": 538, "quantity": 1, "location": 5753, "weight": 0.249}, {"item": 692, "quantity": 1, "location": 284, "weight": 0.312}, {"item": 381, "quantity": 1, "location": 2806, "weight": 0.943}, {"item": 556, "quantity": 2, "location": 293, "weight": 0.726}, {"item": 176, "quantity": 2, "location": 673, "weight": 0.983}, {"item": 292, "quantity": 2, "location": 305, "weight": 1.865}, {"item": 33, "quantity": 2, "location": 3232, "weight": 0.867}, {"item": 73, "quantity": 2, "location": 3598, "weight": 0.621}]}, {"order_id": 47, "num_orderlines": 6, "total_weight": 4.909, "orderlines": [{"item": 377, "quantity": 2, "location": 6475, "weight": 0.988}, {"item": 826, "quantity": 1, "location": 4637, "weight": 0.636}, {"item": 219, "quantity": 2, "location": 672, "weight": 0.916}, {"item": 12, "quantity": 2, "location": 2506, "weight": 1.359}, {"item": 763, "quantity": 2, "location": 3937, "weight": 0.449}, {"item": 499, "quantity": 1, "location": 2069, "weight": 0.561}]}, {"order_id": 48, "num_orderlines": 4, "total_weight": 5.355, "orderlines": [{"item": 335, "quantity": 2, "location": 6456, "weight": 1.306}, {"item": 18, "quantity": 2, "location": 2498, "weight": 1.69}, {"item": 333, "quantity": 2, "location": 636, "weight": 1.749}, {"item": 835, "quantity": 1, "location": 3226, "weight": 0.61}]}, {"order_id": 49, "num_orderlines": 5, "total_weight": 4.218, "orderlines": [{"item": 45, "quantity": 2, "location": 325, "weight": 1.649}, {"item": 76, "quantity": 2, "location": 341, "weight": 0.728}, {"item": 9, "quantity": 2, "location": 339, "weight": 1.011}, {"item": 426, "quantity": 1, "location": 3915, "weight": 0.315}, {"item": 87, "quantity": 1, "location": 2124, "weight": 0.516}]}, {"order_id": 50, "num_orderlines": 8, "total_weight": 7.185, "orderlines": [{"item": 147, "quantity": 2, "location": 2125, "weight": 1.137}, {"item": 226, "quantity": 1, "location": 1768, "weight": 0.122}, {"item": 419, "quantity": 2, "location": 5363, "weight": 1.839}, {"item": 196, "quantity": 1, "location": 1052, "weight": 0.639}, {"item": 849, "quantity": 2, "location": 5039, "weight": 1.931}, {"item": 67, "quantity": 1, "location": 2517, "weight": 0.374}, {"item": 603, "quantity": 1, "location": 4284, "weight": 0.749}, {"item": 160, "quantity": 2, "location": 2496, "weight": 0.394}]}, {"order_id": 51, "num_orderlines": 2, "total_weight": 2.059, "orderlines": [{"item": 572, "quantity": 2, "location": 2792, "weight": 1.069}, {"item": 1, "quantity": 2, "location": 313, "weight": 0.99}]}, {"order_id": 52, "num_orderlines": 10, "total_weight": 7.236, "orderlines": [{"item": 44, "quantity": 1, "location": 707, "weight": 0.849}, {"item": 53, "quantity": 1, "location": 1061, "weight": 0.698}, {"item": 170, "quantity": 2, "location": 331, "weight": 0.724}, {"item": 59, "quantity": 1, "location": 324, "weight": 0.203}, {"item": 593, "quantity": 1, "location": 5723, "weight": 0.639}, {"item": 143, "quantity": 1, "location": 662, "weight": 0.615}, {"item": 341, "quantity": 1, "location": 5736, "weight": 0.963}, {"item": 46, "quantity": 1, "location": 2864, "weight": 0.449}, {"item": 48, "quantity": 2, "location": 664, "weight": 1.428}, {"item": 750, "quantity": 2, "location": 655, "weight": 0.669}]}, {"order_id": 53, "num_orderlines": 3, "total_weight": 2.599, "orderlines": [{"item": 179, "quantity": 1, "location": 1788, "weight": 0.774}, {"item": 407, "quantity": 2, "location": 2830, "weight": 1.706}, {"item": 269, "quantity": 1, "location": 2861, "weight": 0.119}]}, {"order_id": 54, "num_orderlines": 3, "total_weight": 2.722, "orderlines": [{"item": 74, "quantity": 2, "location": 1780, "weight": 0.305}, {"item": 28, "quantity": 2, "location": 1067, "weight": 0.478}, {"item": 232, "quantity": 2, "location": 2509, "weight": 1.939}]}, {"order_id": 55, "num_orderlines": 3, "total_weight": 2.152, "orderlines": [{"item": 5, "quantity": 1, "location": 1076, "weight": 0.978}, {"item": 21, "quantity": 2, "location": 2513, "weight": 0.838}, {"item": 189, "quantity": 1, "location": 712, "weight": 0.336}]}, {"order_id": 56, "num_orderlines": 3, "total_weight": 1.932, "orderlines": [{"item": 686, "quantity": 1, "location": 994, "weight": 0.478}, {"item": 738, "quantity": 1, "location": 3175, "weight": 0.455}, {"item": 409, "quantity": 1, "location": 5394, "weight": 0.999}]}, {"order_id": 57, "num_orderlines": 5, "total_weight": 3.327, "orderlines": [{"item": 391, "quantity": 1, "location": 2115, "weight": 0.21}, {"item": 567, "quantity": 1, "location": 2443, "weight": 0.152}, {"item": 60, "quantity": 1, "location": 343, "weight": 0.702}, {"item": 296, "quantity": 1, "location": 3231, "weight": 0.982}, {"item": 789, "quantity": 2, "location": 1726, "weight": 1.281}]}, {"order_id": 58, "num_orderlines": 1, "total_weight": 0.523, "orderlines": [{"item": 34, "quantity": 1, "location": 1433, "weight": 0.523}]}, {"order_id": 59, "num_orderlines": 3, "total_weight": 2.263, "orderlines": [{"item": 144, "quantity": 2, "location": 688, "weight": 1.052}, {"item": 351, "quantity": 1, "location": 1752, "weight": 0.254}, {"item": 387, "quantity": 1, "location": 294, "weight": 0.956}]}, {"order_id": 60, "num_orderlines": 8, "total_weight": 4.27, "orderlines": [{"item": 794, "quantity": 1, "location": 3221, "weight": 0.127}, {"item": 688, "quantity": 1, "location": 5741, "weight": 0.777}, {"item": 57, "quantity": 2, "location": 356, "weight": 1.224}, {"item": 127, "quantity": 1, "location": 335, "weight": 0.23}, {"item": 27, "quantity": 2, "location": 2519, "weight": 0.279}, {"item": 238, "quantity": 2, "location": 667, "weight": 0.232}, {"item": 161, "quantity": 1, "location": 1079, "weight": 0.924}, {"item": 365, "quantity": 1, "location": 2122, "weight": 0.477}]}, {"order_id": 61, "num_orderlines": 1, "total_weight": 0.391, "orderlines": [{"item": 229, "quantity": 2, "location": 3590, "weight": 0.391}]}, {"order_id": 62, "num_orderlines": 5, "total_weight": 3.986, "orderlines": [{"item": 0, "quantity": 1, "location": 716, "weight": 0.797}, {"item": 100, "quantity": 1, "location": 327, "weight": 0.918}, {"item": 82, "quantity": 1, "location": 302, "weight": 0.833}, {"item": 348, "quantity": 1, "location": 2102, "weight": 0.631}, {"item": 7, "quantity": 1, "location": 1408, "weight": 0.807}]}, {"order_id": 63, "num_orderlines": 3, "total_weight": 2.373, "orderlines": [{"item": 355, "quantity": 2, "location": 2440, "weight": 1.141}, {"item": 91, "quantity": 1, "location": 1781, "weight": 0.727}, {"item": 9, "quantity": 1, "location": 339, "weight": 0.505}]}, {"order_id": 64, "num_orderlines": 8, "total_weight": 6.309, "orderlines": [{"item": 358, "quantity": 2, "location": 1733, "weight": 1.086}, {"item": 69, "quantity": 1, "location": 699, "weight": 0.493}, {"item": 332, "quantity": 1, "location": 2088, "weight": 0.725}, {"item": 29, "quantity": 2, "location": 718, "weight": 1.429}, {"item": 164, "quantity": 2, "location": 310, "weight": 1.199}, {"item": 38, "quantity": 1, "location": 1434, "weight": 0.304}, {"item": 372, "quantity": 2, "location": 6478, "weight": 0.856}, {"item": 36, "quantity": 1, "location": 2500, "weight": 0.217}]}, {"order_id": 65, "num_orderlines": 1, "total_weight": 0.821, "orderlines": [{"item": 425, "quantity": 1, "location": 2059, "weight": 0.821}]}, {"order_id": 66, "num_orderlines": 10, "total_weight": 7.161, "orderlines": [{"item": 607, "quantity": 1, "location": 298, "weight": 0.203}, {"item": 157, "quantity": 1, "location": 1798, "weight": 0.694}, {"item": 8, "quantity": 2, "location": 1071, "weight": 0.431}, {"item": 206, "quantity": 1, "location": 671, "weight": 0.219}, {"item": 423, "quantity": 1, "location": 1710, "weight": 0.146}, {"item": 560, "quantity": 2, "location": 6092, "weight": 0.351}, {"item": 284, "quantity": 2, "location": 669, "weight": 1.228}, {"item": 654, "quantity": 1, "location": 2821, "weight": 0.868}, {"item": 153, "quantity": 2, "location": 3234, "weight": 1.197}, {"item": 109, "quantity": 2, "location": 713, "weight": 1.825}]}, {"order_id": 67, "num_orderlines": 2, "total_weight": 1.195, "orderlines": [{"item": 213, "quantity": 1, "location": 1437, "weight": 0.824}, {"item": 400, "quantity": 1, "location": 6107, "weight": 0.372}]}, {"order_id": 68, "num_orderlines": 9, "total_weight": 7.801, "orderlines": [{"item": 40, "quantity": 1, "location": 2875, "weight": 0.493}, {"item": 0, "quantity": 2, "location": 716, "weight": 1.593}, {"item": 98, "quantity": 1, "location": 308, "weight": 0.206}, {"item": 631, "quantity": 1, "location": 2091, "weight": 0.84}, {"item": 12, "quantity": 2, "location": 2506, "weight": 1.359}, {"item": 11, "quantity": 1, "location": 307, "weight": 0.934}, {"item": 126, "quantity": 2, "location": 2512, "weight": 0.794}, {"item": 457, "quantity": 2, "location": 3574, "weight": 1.025}, {"item": 209, "quantity": 1, "location": 2140, "weight": 0.556}]}, {"order_id": 69, "num_orderlines": 6, "total_weight": 7.211, "orderlines": [{"item": 476, "quantity": 2, "location": 4652, "weight": 0.97}, {"item": 6, "quantity": 2, "location": 1393, "weight": 1.57}, {"item": 424, "quantity": 1, "location": 1699, "weight": 0.645}, {"item": 5, "quantity": 2, "location": 1076, "weight": 1.956}, {"item": 16, "quantity": 2, "location": 1398, "weight": 1.198}, {"item": 633, "quantity": 2, "location": 1007, "weight": 0.871}]}, {"order_id": 70, "num_orderlines": 3, "total_weight": 1.355, "orderlines": [{"item": 316, "quantity": 1, "location": 249, "weight": 0.442}, {"item": 325, "quantity": 1, "location": 1364, "weight": 0.687}, {"item": 309, "quantity": 1, "location": 4644, "weight": 0.226}]}, {"order_id": 71, "num_orderlines": 4, "total_weight": 3.668, "orderlines": [{"item": 464, "quantity": 1, "location": 2484, "weight": 0.62}, {"item": 20, "quantity": 1, "location": 2874, "weight": 0.782}, {"item": 0, "quantity": 1, "location": 716, "weight": 0.797}, {"item": 54, "quantity": 2, "location": 2159, "weight": 1.469}]}, {"order_id": 72, "num_orderlines": 1, "total_weight": 1.27, "orderlines": [{"item": 259, "quantity": 2, "location": 2505, "weight": 1.27}]}, {"order_id": 73, "num_orderlines": 9, "total_weight": 7.824, "orderlines": [{"item": 129, "quantity": 2, "location": 1428, "weight": 1.258}, {"item": 298, "quantity": 2, "location": 1064, "weight": 1.603}, {"item": 191, "quantity": 2, "location": 1037, "weight": 0.634}, {"item": 14, "quantity": 2, "location": 693, "weight": 0.998}, {"item": 125, "quantity": 1, "location": 3233, "weight": 0.545}, {"item": 132, "quantity": 1, "location": 1410, "weight": 0.623}, {"item": 691, "quantity": 1, "location": 4255, "weight": 0.907}, {"item": 751, "quantity": 2, "location": 2815, "weight": 0.78}, {"item": 194, "quantity": 2, "location": 2499, "weight": 0.476}]}, {"order_id": 74, "num_orderlines": 9, "total_weight": 10.258, "orderlines": [{"item": 80, "quantity": 2, "location": 1053, "weight": 1.396}, {"item": 357, "quantity": 2, "location": 5366, "weight": 1.639}, {"item": 630, "quantity": 1, "location": 3567, "weight": 0.932}, {"item": 311, "quantity": 2, "location": 2093, "weight": 0.95}, {"item": 103, "quantity": 1, "location": 2860, "weight": 0.972}, {"item": 102, "quantity": 2, "location": 2859, "weight": 0.679}, {"item": 5, "quantity": 2, "location": 1076, "weight": 1.956}, {"item": 30, "quantity": 2, "location": 2130, "weight": 1.541}, {"item": 128, "quantity": 1, "location": 2879, "weight": 0.193}]}, {"order_id": 75, "num_orderlines": 10, "total_weight": 6.264, "orderlines": [{"item": 75, "quantity": 1, "location": 676, "weight": 0.353}, {"item": 220, "quantity": 1, "location": 719, "weight": 0.371}, {"item": 124, "quantity": 2, "location": 1065, "weight": 0.275}, {"item": 625, "quantity": 1, "location": 2120, "weight": 0.47}, {"item": 47, "quantity": 1, "location": 2154, "weight": 0.359}, {"item": 120, "quantity": 1, "location": 1427, "weight": 0.626}, {"item": 247, "quantity": 1, "location": 717, "weight": 0.471}, {"item": 772, "quantity": 2, "location": 5396, "weight": 1.262}, {"item": 2, "quantity": 2, "location": 340, "weight": 1.745}, {"item": 172, "quantity": 1, "location": 318, "weight": 0.33}]}, {"order_id": 76, "num_orderlines": 1, "total_weight": 1.098, "orderlines": [{"item": 580, "quantity": 2, "location": 4318, "weight": 1.098}]}, {"order_id": 77, "num_orderlines": 8, "total_weight": 9.449, "orderlines": [{"item": 0, "quantity": 2, "location": 716, "weight": 1.593}, {"item": 119, "quantity": 2, "location": 352, "weight": 1.329}, {"item": 11, "quantity": 2, "location": 307, "weight": 1.868}, {"item": 796, "quantity": 1, "location": 1031, "weight": 0.117}, {"item": 714, "quantity": 1, "location": 2075, "weight": 0.809}, {"item": 480, "quantity": 1, "location": 3535, "weight": 0.468}, {"item": 319, "quantity": 2, "location": 4984, "weight": 1.908}, {"item": 299, "quantity": 2, "location": 2873, "weight": 1.356}]}, {"order_id": 78, "num_orderlines": 3, "total_weight": 1.12, "orderlines": [{"item": 825, "quantity": 1, "location": 2794, "weight": 0.116}, {"item": 704, "quantity": 2, "location": 1705, "weight": 0.71}, {"item": 291, "quantity": 2, "location": 2157, "weight": 0.294}]}, {"order_id": 79, "num_orderlines": 3, "total_weight": 2.119, "orderlines": [{"item": 2, "quantity": 1, "location": 340, "weight": 0.873}, {"item": 96, "quantity": 2, "location": 2501, "weight": 0.851}, {"item": 322, "quantity": 1, "location": 605, "weight": 0.396}]}, {"order_id": 80, "num_orderlines": 5, "total_weight": 2.995, "orderlines": [{"item": 0, "quantity": 1, "location": 716, "weight": 0.797}, {"item": 1, "quantity": 1, "location": 313, "weight": 0.495}, {"item": 141, "quantity": 1, "location": 1401, "weight": 0.542}, {"item": 123, "quantity": 1, "location": 2510, "weight": 0.474}, {"item": 718, "quantity": 1, "location": 2445, "weight": 0.688}]}, {"order_id": 81, "num_orderlines": 4, "total_weight": 3.788, "orderlines": [{"item": 694, "quantity": 1, "location": 6110, "weight": 0.918}, {"item": 4, "quantity": 2, "location": 680, "weight": 0.37}, {"item": 0, "quantity": 2, "location": 716, "weight": 1.593}, {"item": 413, "quantity": 1, "location": 985, "weight": 0.907}]}, {"order_id": 82, "num_orderlines": 9, "total_weight": 7.765, "orderlines": [{"item": 7, "quantity": 2, "location": 1408, "weight": 1.615}, {"item": 34, "quantity": 1, "location": 1433, "weight": 0.523}, {"item": 842, "quantity": 1, "location": 5744, "weight": 0.568}, {"item": 0, "quantity": 2, "location": 716, "weight": 1.593}, {"item": 26, "quantity": 1, "location": 1040, "weight": 0.52}, {"item": 37, "quantity": 2, "location": 2147, "weight": 1.056}, {"item": 539, "quantity": 1, "location": 3525, "weight": 0.853}, {"item": 805, "quantity": 1, "location": 3902, "weight": 0.229}, {"item": 52, "quantity": 1, "location": 1397, "weight": 0.808}]}, {"order_id": 83, "num_orderlines": 10, "total_weight": 11.342, "orderlines": [{"item": 0, "quantity": 2, "location": 716, "weight": 1.593}, {"item": 29, "quantity": 2, "location": 718, "weight": 1.429}, {"item": 2, "quantity": 1, "location": 340, "weight": 0.873}, {"item": 248, "quantity": 2, "location": 1066, "weight": 0.874}, {"item": 55, "quantity": 1, "location": 1782, "weight": 0.803}, {"item": 158, "quantity": 2, "location": 315, "weight": 1.509}, {"item": 1, "quantity": 1, "location": 313, "weight": 0.495}, {"item": 58, "quantity": 2, "location": 675, "weight": 0.452}, {"item": 12, "quantity": 2, "location": 2506, "weight": 1.359}, {"item": 5, "quantity": 2, "location": 1076, "weight": 1.956}]}, {"order_id": 84, "num_orderlines": 7, "total_weight": 3.794, "orderlines": [{"item": 646, "quantity": 2, "location": 3900, "weight": 0.208}, {"item": 276, "quantity": 2, "location": 1077, "weight": 0.772}, {"item": 1, "quantity": 1, "location": 313, "weight": 0.495}, {"item": 177, "quantity": 1, "location": 1419, "weight": 0.993}, {"item": 254, "quantity": 1, "location": 715, "weight": 0.313}, {"item": 0, "quantity": 1, "location": 716, "weight": 0.797}, {"item": 8, "quantity": 1, "location": 1071, "weight": 0.215}]}, {"order_id": 85, "num_orderlines": 2, "total_weight": 2.583, "orderlines": [{"item": 0, "quantity": 2, "location": 716, "weight": 1.593}, {"item": 1, "quantity": 2, "location": 313, "weight": 0.99}]}]}