{"scenario": 1, "period": 3, "subperiod": 7, "num_orders": 80, "orders": [{"order_id": 0, "num_orderlines": 7, "total_weight": 23.094, "orderlines": [{"item": 206, "quantity": 5, "location": 671, "weight": 1.093}, {"item": 184, "quantity": 2, "location": 3239, "weight": 1.59}, {"item": 491, "quantity": 6, "location": 625, "weight": 4.099}, {"item": 262, "quantity": 4, "location": 1395, "weight": 1.517}, {"item": 202, "quantity": 4, "location": 3596, "weight": 2.203}, {"item": 360, "quantity": 6, "location": 2850, "weight": 5.629}, {"item": 179, "quantity": 9, "location": 1788, "weight": 6.963}]}, {"order_id": 1, "num_orderlines": 5, "total_weight": 21.231, "orderlines": [{"item": 60, "quantity": 7, "location": 343, "weight": 4.911}, {"item": 46, "quantity": 4, "location": 2864, "weight": 1.795}, {"item": 573, "quantity": 7, "location": 6095, "weight": 5.543}, {"item": 176, "quantity": 6, "location": 673, "weight": 2.95}, {"item": 66, "quantity": 10, "location": 3599, "weight": 6.033}]}, {"order_id": 2, "num_orderlines": 7, "total_weight": 17.469, "orderlines": [{"item": 152, "quantity": 7, "location": 1036, "weight": 1.583}, {"item": 132, "quantity": 8, "location": 1410, "weight": 4.984}, {"item": 100, "quantity": 2, "location": 327, "weight": 1.835}, {"item": 6, "quantity": 4, "location": 1393, "weight": 3.14}, {"item": 292, "quantity": 5, "location": 305, "weight": 4.662}, {"item": 269, "quantity": 2, "location": 2861, "weight": 0.238}, {"item": 56, "quantity": 2, "location": 2869, "weight": 1.026}]}, {"order_id": 3, "num_orderlines": 4, "total_weight": 11.963, "orderlines": [{"item": 14, "quantity": 10, "location": 693, "weight": 4.991}, {"item": 399, "quantity": 1, "location": 4633, "weight": 0.498}, {"item": 138, "quantity": 7, "location": 3230, "weight": 5.631}, {"item": 192, "quantity": 4, "location": 2133, "weight": 0.842}]}, {"order_id": 4, "num_orderlines": 7, "total_weight": 20.74, "orderlines": [{"item": 236, "quantity": 8, "location": 1773, "weight": 4.165}, {"item": 395, "quantity": 4, "location": 1332, "weight": 2.036}, {"item": 113, "quantity": 3, "location": 358, "weight": 1.864}, {"item": 6, "quantity": 3, "location": 1393, "weight": 2.355}, {"item": 89, "quantity": 8, "location": 1791, "weight": 4.407}, {"item": 234, "quantity": 6, "location": 1425, "weight": 5.638}, {"item": 25, "quantity": 1, "location": 1041, "weight": 0.275}]}, {"order_id": 5, "num_orderlines": 4, "total_weight": 13.578, "orderlines": [{"item": 436, "quantity": 10, "location": 5009, "weight": 2.124}, {"item": 58, "quantity": 8, "location": 675, "weight": 1.806}, {"item": 108, "quantity": 9, "location": 2149, "weight": 1.681}, {"item": 0, "quantity": 10, "location": 716, "weight": 7.966}]}, {"order_id": 6, "num_orderlines": 8, "total_weight": 19.987, "orderlines": [{"item": 118, "quantity": 3, "location": 3594, "weight": 1.467}, {"item": 0, "quantity": 6, "location": 716, "weight": 4.78}, {"item": 20, "quantity": 5, "location": 2874, "weight": 3.912}, {"item": 73, "quantity": 9, "location": 3598, "weight": 2.795}, {"item": 255, "quantity": 2, "location": 1418, "weight": 1.543}, {"item": 3, "quantity": 1, "location": 700, "weight": 0.728}, {"item": 107, "quantity": 8, "location": 678, "weight": 2.76}, {"item": 732, "quantity": 10, "location": 4666, "weight": 2.004}]}, {"order_id": 7, "num_orderlines": 1, "total_weight": 1.193, "orderlines": [{"item": 421, "quantity": 9, "location": 1009, "weight": 1.193}]}, {"order_id": 8, "num_orderlines": 2, "total_weight": 3.812, "orderlines": [{"item": 670, "quantity": 10, "location": 2833, "weight": 2.231}, {"item": 309, "quantity": 7, "location": 4644, "weight": 1.581}]}, {"order_id": 9, "num_orderlines": 4, "total_weight": 13.9, "orderlines": [{"item": 43, "quantity": 3, "location": 689, "weight": 1.143}, {"item": 0, "quantity": 7, "location": 716, "weight": 5.576}, {"item": 80, "quantity": 9, "location": 1053, "weight": 6.281}, {"item": 270, "quantity": 6, "location": 1769, "weight": 0.899}]}, {"order_id": 10, "num_orderlines": 4, "total_weight": 13.183, "orderlines": [{"item": 46, "quantity": 2, "location": 2864, "weight": 0.897}, {"item": 0, "quantity": 9, "location": 716, "weight": 7.169}, {"item": 1, "quantity": 7, "location": 313, "weight": 3.465}, {"item": 25, "quantity": 6, "location": 1041, "weight": 1.651}]}, {"order_id": 11, "num_orderlines": 9, "total_weight": 27.827, "orderlines": [{"item": 3, "quantity": 5, "location": 700, "weight": 3.638}, {"item": 345, "quantity": 9, "location": 4285, "weight": 7.34}, {"item": 74, "quantity": 5, "location": 1780, "weight": 0.762}, {"item": 170, "quantity": 8, "location": 331, "weight": 2.894}, {"item": 0, "quantity": 8, "location": 716, "weight": 6.373}, {"item": 35, "quantity": 7, "location": 301, "weight": 1.894}, {"item": 363, "quantity": 2, "location": 254, "weight": 0.358}, {"item": 353, "quantity": 6, "location": 1697, "weight": 3.691}, {"item": 742, "quantity": 1, "location": 1757, "weight": 0.876}]}, {"order_id": 12, "num_orderlines": 8, "total_weight": 21.439, "orderlines": [{"item": 37, "quantity": 8, "location": 2147, "weight": 4.225}, {"item": 0, "quantity": 6, "location": 716, "weight": 4.78}, {"item": 303, "quantity": 4, "location": 987, "weight": 2.251}, {"item": 67, "quantity": 1, "location": 2517, "weight": 0.374}, {"item": 340, "quantity": 5, "location": 5382, "weight": 1.119}, {"item": 346, "quantity": 6, "location": 607, "weight": 5.708}, {"item": 40, "quantity": 2, "location": 2875, "weight": 0.987}, {"item": 768, "quantity": 10, "location": 5004, "weight": 1.996}]}, {"order_id": 13, "num_orderlines": 8, "total_weight": 22.373, "orderlines": [{"item": 156, "quantity": 10, "location": 1414, "weight": 3.531}, {"item": 72, "quantity": 1, "location": 1415, "weight": 0.868}, {"item": 228, "quantity": 5, "location": 309, "weight": 3.353}, {"item": 12, "quantity": 8, "location": 2506, "weight": 5.436}, {"item": 157, "quantity": 10, "location": 1798, "weight": 6.935}, {"item": 347, "quantity": 2, "location": 7188, "weight": 0.656}, {"item": 26, "quantity": 2, "location": 1040, "weight": 1.04}, {"item": 4, "quantity": 3, "location": 680, "weight": 0.554}]}, {"order_id": 14, "num_orderlines": 7, "total_weight": 25.767, "orderlines": [{"item": 21, "quantity": 1, "location": 2513, "weight": 0.419}, {"item": 92, "quantity": 5, "location": 1060, "weight": 2.507}, {"item": 339, "quantity": 6, "location": 2107, "weight": 5.654}, {"item": 465, "quantity": 10, "location": 2098, "weight": 7.298}, {"item": 711, "quantity": 9, "location": 2471, "weight": 6.364}, {"item": 25, "quantity": 9, "location": 1041, "weight": 2.477}, {"item": 61, "quantity": 2, "location": 333, "weight": 1.048}]}, {"order_id": 15, "num_orderlines": 10, "total_weight": 32.981, "orderlines": [{"item": 48, "quantity": 1, "location": 664, "weight": 0.714}, {"item": 131, "quantity": 1, "location": 2152, "weight": 0.933}, {"item": 45, "quantity": 4, "location": 325, "weight": 3.297}, {"item": 53, "quantity": 9, "location": 1061, "weight": 6.286}, {"item": 47, "quantity": 10, "location": 2154, "weight": 3.595}, {"item": 163, "quantity": 7, "location": 670, "weight": 0.936}, {"item": 17, "quantity": 4, "location": 323, "weight": 0.63}, {"item": 31, "quantity": 9, "location": 1403, "weight": 8.737}, {"item": 186, "quantity": 4, "location": 1034, "weight": 1.745}, {"item": 2, "quantity": 7, "location": 340, "weight": 6.109}]}, {"order_id": 16, "num_orderlines": 6, "total_weight": 31.756, "orderlines": [{"item": 0, "quantity": 9, "location": 716, "weight": 7.169}, {"item": 79, "quantity": 9, "location": 1793, "weight": 7.25}, {"item": 19, "quantity": 7, "location": 1787, "weight": 4.679}, {"item": 3, "quantity": 9, "location": 700, "weight": 6.548}, {"item": 27, "quantity": 5, "location": 2519, "weight": 0.697}, {"item": 78, "quantity": 9, "location": 681, "weight": 5.412}]}, {"order_id": 17, "num_orderlines": 8, "total_weight": 32.224, "orderlines": [{"item": 283, "quantity": 8, "location": 3595, "weight": 2.595}, {"item": 42, "quantity": 4, "location": 1774, "weight": 2.921}, {"item": 239, "quantity": 3, "location": 3593, "weight": 0.595}, {"item": 3, "quantity": 6, "location": 700, "weight": 4.366}, {"item": 540, "quantity": 8, "location": 1736, "weight": 7.922}, {"item": 183, "quantity": 10, "location": 2865, "weight": 3.843}, {"item": 29, "quantity": 3, "location": 718, "weight": 2.144}, {"item": 115, "quantity": 9, "location": 1033, "weight": 7.839}]}, {"order_id": 18, "num_orderlines": 6, "total_weight": 17.446, "orderlines": [{"item": 122, "quantity": 3, "location": 1044, "weight": 0.528}, {"item": 311, "quantity": 4, "location": 2093, "weight": 1.901}, {"item": 16, "quantity": 4, "location": 1398, "weight": 2.396}, {"item": 241, "quantity": 7, "location": 1777, "weight": 5.72}, {"item": 51, "quantity": 6, "location": 2135, "weight": 0.64}, {"item": 77, "quantity": 9, "location": 702, "weight": 6.261}]}, {"order_id": 19, "num_orderlines": 1, "total_weight": 0.734, "orderlines": [{"item": 291, "quantity": 5, "location": 2157, "weight": 0.734}]}, {"order_id": 20, "num_orderlines": 1, "total_weight": 1.113, "orderlines": [{"item": 220, "quantity": 3, "location": 719, "weight": 1.113}]}, {"order_id": 21, "num_orderlines": 10, "total_weight": 31.733, "orderlines": [{"item": 364, "quantity": 10, "location": 2468, "weight": 6.921}, {"item": 257, "quantity": 7, "location": 1042, "weight": 1.364}, {"item": 124, "quantity": 5, "location": 1065, "weight": 0.688}, {"item": 57, "quantity": 1, "location": 356, "weight": 0.612}, {"item": 110, "quantity": 10, "location": 2504, "weight": 5.102}, {"item": 15, "quantity": 5, "location": 1070, "weight": 1.522}, {"item": 0, "quantity": 5, "location": 716, "weight": 3.983}, {"item": 278, "quantity": 6, "location": 1032, "weight": 5.325}, {"item": 10, "quantity": 9, "location": 2148, "weight": 3.903}, {"item": 172, "quantity": 7, "location": 318, "weight": 2.313}]}, {"order_id": 22, "num_orderlines": 9, "total_weight": 21.192, "orderlines": [{"item": 754, "quantity": 3, "location": 991, "weight": 2.145}, {"item": 112, "quantity": 2, "location": 321, "weight": 0.751}, {"item": 371, "quantity": 1, "location": 1336, "weight": 0.344}, {"item": 538, "quantity": 9, "location": 5753, "weight": 2.244}, {"item": 7, "quantity": 2, "location": 1408, "weight": 1.615}, {"item": 16, "quantity": 9, "location": 1398, "weight": 5.392}, {"item": 374, "quantity": 10, "location": 288, "weight": 2.419}, {"item": 229, "quantity": 6, "location": 3590, "weight": 1.172}, {"item": 42, "quantity": 7, "location": 1774, "weight": 5.111}]}, {"order_id": 23, "num_orderlines": 1, "total_weight": 2.032, "orderlines": [{"item": 58, "quantity": 9, "location": 675, "weight": 2.032}]}, {"order_id": 24, "num_orderlines": 4, "total_weight": 15.775, "orderlines": [{"item": 86, "quantity": 9, "location": 1789, "weight": 6.751}, {"item": 263, "quantity": 2, "location": 1413, "weight": 0.459}, {"item": 0, "quantity": 10, "location": 716, "weight": 7.966}, {"item": 16, "quantity": 1, "location": 1398, "weight": 0.599}]}, {"order_id": 25, "num_orderlines": 1, "total_weight": 0.797, "orderlines": [{"item": 0, "quantity": 1, "location": 716, "weight": 0.797}]}, {"order_id": 26, "num_orderlines": 7, "total_weight": 28.035, "orderlines": [{"item": 359, "quantity": 8, "location": 2797, "weight": 5.117}, {"item": 401, "quantity": 1, "location": 3541, "weight": 0.927}, {"item": 37, "quantity": 9, "location": 2147, "weight": 4.753}, {"item": 147, "quantity": 10, "location": 2125, "weight": 5.686}, {"item": 0, "quantity": 8, "location": 716, "weight": 6.373}, {"item": 182, "quantity": 4, "location": 1039, "weight": 2.268}, {"item": 31, "quantity": 3, "location": 1403, "weight": 2.912}]}, {"order_id": 27, "num_orderlines": 10, "total_weight": 31.024, "orderlines": [{"item": 70, "quantity": 2, "location": 1429, "weight": 0.586}, {"item": 12, "quantity": 1, "location": 2506, "weight": 0.679}, {"item": 402, "quantity": 6, "location": 3192, "weight": 4.819}, {"item": 203, "quantity": 6, "location": 2516, "weight": 1.377}, {"item": 334, "quantity": 10, "location": 5397, "weight": 2.189}, {"item": 6, "quantity": 6, "location": 1393, "weight": 4.71}, {"item": 187, "quantity": 8, "location": 329, "weight": 1.48}, {"item": 59, "quantity": 7, "location": 324, "weight": 1.422}, {"item": 326, "quantity": 8, "location": 3542, "weight": 6.592}, {"item": 0, "quantity": 9, "location": 716, "weight": 7.169}]}, {"order_id": 28, "num_orderlines": 4, "total_weight": 17.892, "orderlines": [{"item": 177, "quantity": 10, "location": 1419, "weight": 9.931}, {"item": 387, "quantity": 4, "location": 294, "weight": 3.824}, {"item": 123, "quantity": 5, "location": 2510, "weight": 2.371}, {"item": 75, "quantity": 5, "location": 676, "weight": 1.766}]}, {"order_id": 29, "num_orderlines": 7, "total_weight": 26.842, "orderlines": [{"item": 95, "quantity": 10, "location": 1764, "weight": 6.673}, {"item": 1, "quantity": 3, "location": 313, "weight": 1.485}, {"item": 6, "quantity": 7, "location": 1393, "weight": 5.495}, {"item": 212, "quantity": 1, "location": 1055, "weight": 0.28}, {"item": 142, "quantity": 10, "location": 1069, "weight": 9.44}, {"item": 734, "quantity": 8, "location": 6093, "weight": 1.236}, {"item": 174, "quantity": 9, "location": 345, "weight": 2.233}]}, {"order_id": 30, "num_orderlines": 8, "total_weight": 26.153, "orderlines": [{"item": 8, "quantity": 1, "location": 1071, "weight": 0.215}, {"item": 207, "quantity": 6, "location": 2515, "weight": 4.259}, {"item": 166, "quantity": 3, "location": 692, "weight": 2.54}, {"item": 130, "quantity": 2, "location": 2868, "weight": 0.507}, {"item": 2, "quantity": 7, "location": 340, "weight": 6.109}, {"item": 20, "quantity": 8, "location": 2874, "weight": 6.258}, {"item": 0, "quantity": 6, "location": 716, "weight": 4.78}, {"item": 349, "quantity": 8, "location": 3581, "weight": 1.484}]}, {"order_id": 31, "num_orderlines": 5, "total_weight": 17.114, "orderlines": [{"item": 396, "quantity": 5, "location": 6830, "weight": 4.215}, {"item": 3, "quantity": 6, "location": 700, "weight": 4.366}, {"item": 169, "quantity": 3, "location": 1432, "weight": 2.873}, {"item": 376, "quantity": 5, "location": 1390, "weight": 4.713}, {"item": 90, "quantity": 4, "location": 1074, "weight": 0.948}]}, {"order_id": 32, "num_orderlines": 7, "total_weight": 22.976, "orderlines": [{"item": 39, "quantity": 10, "location": 1073, "weight": 7.028}, {"item": 357, "quantity": 10, "location": 5366, "weight": 8.193}, {"item": 76, "quantity": 2, "location": 341, "weight": 0.728}, {"item": 94, "quantity": 2, "location": 1051, "weight": 0.743}, {"item": 2, "quantity": 5, "location": 340, "weight": 4.364}, {"item": 84, "quantity": 10, "location": 1766, "weight": 1.204}, {"item": 28, "quantity": 3, "location": 1067, "weight": 0.717}]}, {"order_id": 33, "num_orderlines": 2, "total_weight": 4.341, "orderlines": [{"item": 180, "quantity": 4, "location": 359, "weight": 3.607}, {"item": 54, "quantity": 1, "location": 2159, "weight": 0.735}]}, {"order_id": 34, "num_orderlines": 4, "total_weight": 14.253, "orderlines": [{"item": 0, "quantity": 8, "location": 716, "weight": 6.373}, {"item": 168, "quantity": 8, "location": 311, "weight": 3.083}, {"item": 65, "quantity": 7, "location": 2862, "weight": 4.187}, {"item": 74, "quantity": 4, "location": 1780, "weight": 0.61}]}, {"order_id": 35, "num_orderlines": 1, "total_weight": 2.498, "orderlines": [{"item": 82, "quantity": 3, "location": 302, "weight": 2.498}]}, {"order_id": 36, "num_orderlines": 8, "total_weight": 23.166, "orderlines": [{"item": 11, "quantity": 2, "location": 307, "weight": 1.868}, {"item": 394, "quantity": 9, "location": 1358, "weight": 1.0}, {"item": 93, "quantity": 9, "location": 2876, "weight": 3.986}, {"item": 38, "quantity": 8, "location": 1434, "weight": 2.434}, {"item": 129, "quantity": 1, "location": 1428, "weight": 0.629}, {"item": 325, "quantity": 7, "location": 1364, "weight": 4.811}, {"item": 0, "quantity": 5, "location": 716, "weight": 3.983}, {"item": 1, "quantity": 9, "location": 313, "weight": 4.455}]}, {"order_id": 37, "num_orderlines": 5, "total_weight": 11.975, "orderlines": [{"item": 67, "quantity": 1, "location": 2517, "weight": 0.374}, {"item": 7, "quantity": 5, "location": 1408, "weight": 4.037}, {"item": 104, "quantity": 4, "location": 3235, "weight": 3.204}, {"item": 550, "quantity": 6, "location": 971, "weight": 3.134}, {"item": 509, "quantity": 6, "location": 290, "weight": 1.226}]}, {"order_id": 38, "num_orderlines": 4, "total_weight": 11.652, "orderlines": [{"item": 0, "quantity": 1, "location": 716, "weight": 0.797}, {"item": 1, "quantity": 6, "location": 313, "weight": 2.97}, {"item": 41, "quantity": 5, "location": 2867, "weight": 4.247}, {"item": 3, "quantity": 5, "location": 700, "weight": 3.638}]}, {"order_id": 39, "num_orderlines": 3, "total_weight": 19.852, "orderlines": [{"item": 639, "quantity": 9, "location": 3184, "weight": 7.91}, {"item": 7, "quantity": 5, "location": 1408, "weight": 4.037}, {"item": 385, "quantity": 8, "location": 248, "weight": 7.904}]}, {"order_id": 40, "num_orderlines": 3, "total_weight": 10.467, "orderlines": [{"item": 50, "quantity": 2, "location": 2137, "weight": 0.56}, {"item": 199, "quantity": 7, "location": 1399, "weight": 2.655}, {"item": 151, "quantity": 8, "location": 1043, "weight": 7.252}]}, {"order_id": 41, "num_orderlines": 10, "total_weight": 37.564, "orderlines": [{"item": 245, "quantity": 8, "location": 695, "weight": 7.048}, {"item": 9, "quantity": 5, "location": 339, "weight": 2.526}, {"item": 161, "quantity": 2, "location": 1079, "weight": 1.849}, {"item": 23, "quantity": 9, "location": 1439, "weight": 8.134}, {"item": 280, "quantity": 7, "location": 1784, "weight": 0.974}, {"item": 0, "quantity": 2, "location": 716, "weight": 1.593}, {"item": 593, "quantity": 7, "location": 5723, "weight": 4.47}, {"item": 1, "quantity": 10, "location": 313, "weight": 4.95}, {"item": 106, "quantity": 10, "location": 1035, "weight": 5.044}, {"item": 27, "quantity": 7, "location": 2519, "weight": 0.976}]}, {"order_id": 42, "num_orderlines": 8, "total_weight": 17.152, "orderlines": [{"item": 0, "quantity": 8, "location": 716, "weight": 6.373}, {"item": 765, "quantity": 3, "location": 5729, "weight": 0.325}, {"item": 195, "quantity": 4, "location": 1078, "weight": 1.045}, {"item": 34, "quantity": 1, "location": 1433, "weight": 0.523}, {"item": 35, "quantity": 6, "location": 301, "weight": 1.623}, {"item": 135, "quantity": 10, "location": 354, "weight": 1.205}, {"item": 91, "quantity": 6, "location": 1781, "weight": 4.36}, {"item": 41, "quantity": 2, "location": 2867, "weight": 1.699}]}, {"order_id": 43, "num_orderlines": 9, "total_weight": 30.8, "orderlines": [{"item": 1, "quantity": 2, "location": 313, "weight": 0.99}, {"item": 125, "quantity": 1, "location": 3233, "weight": 0.545}, {"item": 0, "quantity": 7, "location": 716, "weight": 5.576}, {"item": 33, "quantity": 5, "location": 3232, "weight": 2.167}, {"item": 289, "quantity": 8, "location": 1797, "weight": 1.532}, {"item": 193, "quantity": 9, "location": 1046, "weight": 7.632}, {"item": 806, "quantity": 6, "location": 1712, "weight": 4.343}, {"item": 13, "quantity": 7, "location": 1795, "weight": 5.883}, {"item": 15, "quantity": 7, "location": 1070, "weight": 2.131}]}, {"order_id": 44, "num_orderlines": 3, "total_weight": 8.676, "orderlines": [{"item": 165, "quantity": 6, "location": 1794, "weight": 2.603}, {"item": 4, "quantity": 7, "location": 680, "weight": 1.294}, {"item": 0, "quantity": 6, "location": 716, "weight": 4.78}]}, {"order_id": 45, "num_orderlines": 9, "total_weight": 34.463, "orderlines": [{"item": 16, "quantity": 9, "location": 1398, "weight": 5.392}, {"item": 352, "quantity": 5, "location": 5016, "weight": 3.043}, {"item": 277, "quantity": 7, "location": 1058, "weight": 3.879}, {"item": 119, "quantity": 6, "location": 352, "weight": 3.988}, {"item": 0, "quantity": 8, "location": 716, "weight": 6.373}, {"item": 126, "quantity": 5, "location": 2512, "weight": 1.984}, {"item": 1, "quantity": 10, "location": 313, "weight": 4.95}, {"item": 190, "quantity": 1, "location": 2146, "weight": 0.943}, {"item": 5, "quantity": 4, "location": 1076, "weight": 3.912}]}, {"order_id": 46, "num_orderlines": 2, "total_weight": 10.723, "orderlines": [{"item": 0, "quantity": 6, "location": 716, "weight": 4.78}, {"item": 44, "quantity": 7, "location": 707, "weight": 5.943}]}, {"order_id": 47, "num_orderlines": 10, "total_weight": 39.261, "orderlines": [{"item": 2, "quantity": 7, "location": 340, "weight": 6.109}, {"item": 167, "quantity": 9, "location": 2145, "weight": 7.447}, {"item": 211, "quantity": 1, "location": 1402, "weight": 0.623}, {"item": 26, "quantity": 5, "location": 1040, "weight": 2.6}, {"item": 584, "quantity": 6, "location": 5391, "weight": 5.554}, {"item": 114, "quantity": 5, "location": 684, "weight": 1.296}, {"item": 120, "quantity": 7, "location": 1427, "weight": 4.38}, {"item": 315, "quantity": 6, "location": 4293, "weight": 2.368}, {"item": 105, "quantity": 10, "location": 2507, "weight": 7.452}, {"item": 28, "quantity": 6, "location": 1067, "weight": 1.433}]}, {"order_id": 48, "num_orderlines": 2, "total_weight": 7.777, "orderlines": [{"item": 164, "quantity": 5, "location": 310, "weight": 2.997}, {"item": 0, "quantity": 6, "location": 716, "weight": 4.78}]}, {"order_id": 49, "num_orderlines": 5, "total_weight": 25.756, "orderlines": [{"item": 11, "quantity": 9, "location": 307, "weight": 8.407}, {"item": 117, "quantity": 1, "location": 2142, "weight": 0.748}, {"item": 5, "quantity": 7, "location": 1076, "weight": 6.847}, {"item": 260, "quantity": 10, "location": 2129, "weight": 2.316}, {"item": 214, "quantity": 10, "location": 1394, "weight": 7.439}]}, {"order_id": 50, "num_orderlines": 9, "total_weight": 26.837, "orderlines": [{"item": 196, "quantity": 7, "location": 1052, "weight": 4.476}, {"item": 116, "quantity": 3, "location": 3597, "weight": 2.348}, {"item": 0, "quantity": 5, "location": 716, "weight": 3.983}, {"item": 3, "quantity": 1, "location": 700, "weight": 0.728}, {"item": 33, "quantity": 2, "location": 3232, "weight": 0.867}, {"item": 133, "quantity": 9, "location": 322, "weight": 3.71}, {"item": 337, "quantity": 9, "location": 4659, "weight": 6.778}, {"item": 279, "quantity": 1, "location": 334, "weight": 0.866}, {"item": 483, "quantity": 8, "location": 2816, "weight": 3.082}]}, {"order_id": 51, "num_orderlines": 1, "total_weight": 1.615, "orderlines": [{"item": 7, "quantity": 2, "location": 1408, "weight": 1.615}]}, {"order_id": 52, "num_orderlines": 9, "total_weight": 39.619, "orderlines": [{"item": 17, "quantity": 7, "location": 323, "weight": 1.102}, {"item": 11, "quantity": 3, "location": 307, "weight": 2.802}, {"item": 5, "quantity": 9, "location": 1076, "weight": 8.803}, {"item": 144, "quantity": 9, "location": 688, "weight": 4.735}, {"item": 254, "quantity": 2, "location": 715, "weight": 0.626}, {"item": 210, "quantity": 10, "location": 1772, "weight": 7.248}, {"item": 356, "quantity": 10, "location": 993, "weight": 7.875}, {"item": 134, "quantity": 7, "location": 2155, "weight": 4.423}, {"item": 19, "quantity": 3, "location": 1787, "weight": 2.006}]}, {"order_id": 53, "num_orderlines": 10, "total_weight": 28.234, "orderlines": [{"item": 0, "quantity": 9, "location": 716, "weight": 7.169}, {"item": 10, "quantity": 4, "location": 2148, "weight": 1.735}, {"item": 4, "quantity": 3, "location": 680, "weight": 0.554}, {"item": 27, "quantity": 3, "location": 2519, "weight": 0.418}, {"item": 28, "quantity": 2, "location": 1067, "weight": 0.478}, {"item": 109, "quantity": 5, "location": 713, "weight": 4.561}, {"item": 98, "quantity": 4, "location": 308, "weight": 0.825}, {"item": 1, "quantity": 9, "location": 313, "weight": 4.455}, {"item": 384, "quantity": 5, "location": 623, "weight": 2.193}, {"item": 256, "quantity": 7, "location": 2141, "weight": 5.844}]}, {"order_id": 54, "num_orderlines": 8, "total_weight": 29.782, "orderlines": [{"item": 145, "quantity": 5, "location": 1765, "weight": 1.702}, {"item": 155, "quantity": 9, "location": 2514, "weight": 6.345}, {"item": 0, "quantity": 8, "location": 716, "weight": 6.373}, {"item": 137, "quantity": 5, "location": 1438, "weight": 2.671}, {"item": 740, "quantity": 4, "location": 4264, "weight": 0.406}, {"item": 225, "quantity": 5, "location": 711, "weight": 4.662}, {"item": 69, "quantity": 4, "location": 699, "weight": 1.972}, {"item": 7, "quantity": 7, "location": 1408, "weight": 5.652}]}, {"order_id": 55, "num_orderlines": 6, "total_weight": 15.762, "orderlines": [{"item": 24, "quantity": 9, "location": 351, "weight": 7.204}, {"item": 101, "quantity": 5, "location": 1417, "weight": 3.649}, {"item": 150, "quantity": 3, "location": 1430, "weight": 2.531}, {"item": 141, "quantity": 1, "location": 1401, "weight": 0.542}, {"item": 4, "quantity": 6, "location": 680, "weight": 1.109}, {"item": 3, "quantity": 1, "location": 700, "weight": 0.728}]}, {"order_id": 56, "num_orderlines": 8, "total_weight": 32.405, "orderlines": [{"item": 18, "quantity": 7, "location": 2498, "weight": 5.914}, {"item": 81, "quantity": 3, "location": 3589, "weight": 1.397}, {"item": 19, "quantity": 6, "location": 1787, "weight": 4.011}, {"item": 103, "quantity": 4, "location": 2860, "weight": 3.889}, {"item": 429, "quantity": 9, "location": 4626, "weight": 7.388}, {"item": 348, "quantity": 9, "location": 2102, "weight": 5.68}, {"item": 336, "quantity": 4, "location": 296, "weight": 0.742}, {"item": 249, "quantity": 7, "location": 661, "weight": 3.383}]}, {"order_id": 57, "num_orderlines": 6, "total_weight": 21.859, "orderlines": [{"item": 294, "quantity": 5, "location": 353, "weight": 4.296}, {"item": 0, "quantity": 9, "location": 716, "weight": 7.169}, {"item": 62, "quantity": 5, "location": 1779, "weight": 3.043}, {"item": 281, "quantity": 9, "location": 1423, "weight": 2.37}, {"item": 243, "quantity": 8, "location": 2128, "weight": 4.622}, {"item": 149, "quantity": 3, "location": 2138, "weight": 0.358}]}, {"order_id": 58, "num_orderlines": 4, "total_weight": 10.84, "orderlines": [{"item": 68, "quantity": 3, "location": 1406, "weight": 0.383}, {"item": 0, "quantity": 5, "location": 716, "weight": 3.983}, {"item": 381, "quantity": 1, "location": 2806, "weight": 0.943}, {"item": 143, "quantity": 9, "location": 662, "weight": 5.531}]}, {"order_id": 59, "num_orderlines": 9, "total_weight": 24.339, "orderlines": [{"item": 0, "quantity": 6, "location": 716, "weight": 4.78}, {"item": 244, "quantity": 7, "location": 1049, "weight": 4.518}, {"item": 316, "quantity": 3, "location": 249, "weight": 1.325}, {"item": 34, "quantity": 8, "location": 1433, "weight": 4.181}, {"item": 32, "quantity": 2, "location": 701, "weight": 0.786}, {"item": 175, "quantity": 6, "location": 355, "weight": 0.842}, {"item": 318, "quantity": 8, "location": 291, "weight": 2.938}, {"item": 50, "quantity": 4, "location": 2137, "weight": 1.12}, {"item": 136, "quantity": 4, "location": 705, "weight": 3.851}]}, {"order_id": 60, "num_orderlines": 6, "total_weight": 18.073, "orderlines": [{"item": 14, "quantity": 3, "location": 693, "weight": 1.497}, {"item": 0, "quantity": 9, "location": 716, "weight": 7.169}, {"item": 329, "quantity": 4, "location": 604, "weight": 1.437}, {"item": 451, "quantity": 6, "location": 3166, "weight": 5.374}, {"item": 139, "quantity": 5, "location": 1409, "weight": 0.872}, {"item": 8, "quantity": 8, "location": 1071, "weight": 1.722}]}, {"order_id": 61, "num_orderlines": 6, "total_weight": 10.274, "orderlines": [{"item": 49, "quantity": 3, "location": 1411, "weight": 0.677}, {"item": 23, "quantity": 5, "location": 1439, "weight": 4.519}, {"item": 63, "quantity": 2, "location": 319, "weight": 1.577}, {"item": 12, "quantity": 3, "location": 2506, "weight": 2.038}, {"item": 97, "quantity": 1, "location": 2877, "weight": 0.179}, {"item": 372, "quantity": 3, "location": 6478, "weight": 1.283}]}, {"order_id": 62, "num_orderlines": 6, "total_weight": 22.208, "orderlines": [{"item": 668, "quantity": 2, "location": 5019, "weight": 0.733}, {"item": 822, "quantity": 1, "location": 964, "weight": 0.365}, {"item": 30, "quantity": 7, "location": 2130, "weight": 5.392}, {"item": 365, "quantity": 6, "location": 2122, "weight": 2.86}, {"item": 29, "quantity": 7, "location": 718, "weight": 5.003}, {"item": 2, "quantity": 9, "location": 340, "weight": 7.854}]}, {"order_id": 63, "num_orderlines": 6, "total_weight": 20.809, "orderlines": [{"item": 555, "quantity": 5, "location": 3585, "weight": 1.548}, {"item": 52, "quantity": 1, "location": 1397, "weight": 0.808}, {"item": 0, "quantity": 10, "location": 716, "weight": 7.966}, {"item": 517, "quantity": 6, "location": 3560, "weight": 4.61}, {"item": 11, "quantity": 2, "location": 307, "weight": 1.868}, {"item": 536, "quantity": 7, "location": 1355, "weight": 4.008}]}, {"order_id": 64, "num_orderlines": 2, "total_weight": 4.767, "orderlines": [{"item": 71, "quantity": 6, "location": 1776, "weight": 2.806}, {"item": 88, "quantity": 8, "location": 687, "weight": 1.961}]}, {"order_id": 65, "num_orderlines": 5, "total_weight": 14.272, "orderlines": [{"item": 56, "quantity": 6, "location": 2869, "weight": 3.078}, {"item": 15, "quantity": 6, "location": 1070, "weight": 1.827}, {"item": 238, "quantity": 6, "location": 667, "weight": 0.697}, {"item": 1, "quantity": 2, "location": 313, "weight": 0.99}, {"item": 223, "quantity": 8, "location": 2134, "weight": 7.681}]}, {"order_id": 66, "num_orderlines": 2, "total_weight": 13.653, "orderlines": [{"item": 22, "quantity": 9, "location": 1412, "weight": 8.762}, {"item": 5, "quantity": 5, "location": 1076, "weight": 4.89}]}, {"order_id": 67, "num_orderlines": 5, "total_weight": 13.901, "orderlines": [{"item": 85, "quantity": 5, "location": 663, "weight": 0.905}, {"item": 18, "quantity": 2, "location": 2498, "weight": 1.69}, {"item": 8, "quantity": 3, "location": 1071, "weight": 0.646}, {"item": 99, "quantity": 8, "location": 2497, "weight": 7.726}, {"item": 5, "quantity": 3, "location": 1076, "weight": 2.934}]}, {"order_id": 68, "num_orderlines": 3, "total_weight": 10.197, "orderlines": [{"item": 194, "quantity": 10, "location": 2499, "weight": 2.38}, {"item": 398, "quantity": 9, "location": 621, "weight": 4.614}, {"item": 368, "quantity": 8, "location": 614, "weight": 3.202}]}, {"order_id": 69, "num_orderlines": 1, "total_weight": 4.712, "orderlines": [{"item": 173, "quantity": 5, "location": 1062, "weight": 4.712}]}, {"order_id": 70, "num_orderlines": 3, "total_weight": 11.753, "orderlines": [{"item": 2, "quantity": 7, "location": 340, "weight": 6.109}, {"item": 87, "quantity": 8, "location": 2124, "weight": 4.126}, {"item": 36, "quantity": 7, "location": 2500, "weight": 1.518}]}, {"order_id": 71, "num_orderlines": 9, "total_weight": 36.621, "orderlines": [{"item": 11, "quantity": 10, "location": 307, "weight": 9.341}, {"item": 2, "quantity": 9, "location": 340, "weight": 7.854}, {"item": 43, "quantity": 5, "location": 689, "weight": 1.905}, {"item": 330, "quantity": 5, "location": 1700, "weight": 3.807}, {"item": 362, "quantity": 7, "location": 2822, "weight": 1.438}, {"item": 515, "quantity": 10, "location": 3174, "weight": 2.557}, {"item": 3, "quantity": 9, "location": 700, "weight": 6.548}, {"item": 96, "quantity": 5, "location": 2501, "weight": 2.128}, {"item": 850, "quantity": 4, "location": 3583, "weight": 1.042}]}, {"order_id": 72, "num_orderlines": 3, "total_weight": 15.483, "orderlines": [{"item": 248, "quantity": 10, "location": 1066, "weight": 4.368}, {"item": 64, "quantity": 10, "location": 2502, "weight": 6.712}, {"item": 251, "quantity": 5, "location": 306, "weight": 4.404}]}, {"order_id": 73, "num_orderlines": 1, "total_weight": 5.977, "orderlines": [{"item": 380, "quantity": 10, "location": 4631, "weight": 5.977}]}, {"order_id": 74, "num_orderlines": 3, "total_weight": 16.732, "orderlines": [{"item": 261, "quantity": 2, "location": 1072, "weight": 1.684}, {"item": 55, "quantity": 9, "location": 1782, "weight": 7.224}, {"item": 20, "quantity": 10, "location": 2874, "weight": 7.823}]}, {"order_id": 75, "num_orderlines": 5, "total_weight": 18.571, "orderlines": [{"item": 0, "quantity": 6, "location": 716, "weight": 4.78}, {"item": 12, "quantity": 10, "location": 2506, "weight": 6.795}, {"item": 1, "quantity": 7, "location": 313, "weight": 3.465}, {"item": 15, "quantity": 3, "location": 1070, "weight": 0.913}, {"item": 2, "quantity": 3, "location": 340, "weight": 2.618}]}, {"order_id": 76, "num_orderlines": 1, "total_weight": 4.78, "orderlines": [{"item": 0, "quantity": 6, "location": 716, "weight": 4.78}]}, {"order_id": 77, "num_orderlines": 1, "total_weight": 7.966, "orderlines": [{"item": 0, "quantity": 10, "location": 716, "weight": 7.966}]}, {"order_id": 78, "num_orderlines": 1, "total_weight": 4.78, "orderlines": [{"item": 0, "quantity": 6, "location": 716, "weight": 4.78}]}, {"order_id": 79, "num_orderlines": 1, "total_weight": 7.966, "orderlines": [{"item": 0, "quantity": 10, "location": 716, "weight": 7.966}]}]}