{"scenario": 1, "period": 3, "subperiod": 10, "num_orders": 178, "orders": [{"order_id": 0, "num_orderlines": 1, "total_weight": 3.983, "orderlines": [{"item": 0, "quantity": 5, "location": 716, "weight": 3.983}]}, {"order_id": 1, "num_orderlines": 1, "total_weight": 7.169, "orderlines": [{"item": 0, "quantity": 9, "location": 716, "weight": 7.169}]}, {"order_id": 2, "num_orderlines": 2, "total_weight": 0.894, "orderlines": [{"item": 186, "quantity": 1, "location": 1034, "weight": 0.436}, {"item": 74, "quantity": 3, "location": 1780, "weight": 0.458}]}, {"order_id": 3, "num_orderlines": 1, "total_weight": 1.5, "orderlines": [{"item": 86, "quantity": 2, "location": 1789, "weight": 1.5}]}, {"order_id": 4, "num_orderlines": 2, "total_weight": 2.266, "orderlines": [{"item": 53, "quantity": 1, "location": 1061, "weight": 0.698}, {"item": 34, "quantity": 3, "location": 1433, "weight": 1.568}]}, {"order_id": 5, "num_orderlines": 1, "total_weight": 1.98, "orderlines": [{"item": 1, "quantity": 4, "location": 313, "weight": 1.98}]}, {"order_id": 6, "num_orderlines": 1, "total_weight": 3.942, "orderlines": [{"item": 63, "quantity": 5, "location": 319, "weight": 3.942}]}, {"order_id": 7, "num_orderlines": 2, "total_weight": 9.978, "orderlines": [{"item": 0, "quantity": 4, "location": 716, "weight": 3.186}, {"item": 44, "quantity": 8, "location": 707, "weight": 6.792}]}, {"order_id": 8, "num_orderlines": 2, "total_weight": 2.378, "orderlines": [{"item": 238, "quantity": 6, "location": 667, "weight": 0.697}, {"item": 108, "quantity": 9, "location": 2149, "weight": 1.681}]}, {"order_id": 9, "num_orderlines": 2, "total_weight": 8.584, "orderlines": [{"item": 2, "quantity": 4, "location": 340, "weight": 3.491}, {"item": 3, "quantity": 7, "location": 700, "weight": 5.093}]}, {"order_id": 10, "num_orderlines": 1, "total_weight": 0.433, "orderlines": [{"item": 33, "quantity": 1, "location": 3232, "weight": 0.433}]}, {"order_id": 11, "num_orderlines": 2, "total_weight": 6.233, "orderlines": [{"item": 0, "quantity": 1, "location": 716, "weight": 0.797}, {"item": 12, "quantity": 8, "location": 2506, "weight": 5.436}]}, {"order_id": 12, "num_orderlines": 1, "total_weight": 0.845, "orderlines": [{"item": 18, "quantity": 1, "location": 2498, "weight": 0.845}]}, {"order_id": 13, "num_orderlines": 1, "total_weight": 2.97, "orderlines": [{"item": 1, "quantity": 6, "location": 313, "weight": 2.97}]}, {"order_id": 14, "num_orderlines": 1, "total_weight": 1.808, "orderlines": [{"item": 23, "quantity": 2, "location": 1439, "weight": 1.808}]}, {"order_id": 15, "num_orderlines": 1, "total_weight": 0.554, "orderlines": [{"item": 4, "quantity": 3, "location": 680, "weight": 0.554}]}, {"order_id": 16, "num_orderlines": 2, "total_weight": 6.541, "orderlines": [{"item": 64, "quantity": 4, "location": 2502, "weight": 2.685}, {"item": 89, "quantity": 7, "location": 1791, "weight": 3.856}]}, {"order_id": 17, "num_orderlines": 1, "total_weight": 5.006, "orderlines": [{"item": 120, "quantity": 8, "location": 1427, "weight": 5.006}]}, {"order_id": 18, "num_orderlines": 2, "total_weight": 6.377, "orderlines": [{"item": 15, "quantity": 5, "location": 1070, "weight": 1.522}, {"item": 31, "quantity": 5, "location": 1403, "weight": 4.854}]}, {"order_id": 19, "num_orderlines": 2, "total_weight": 8.517, "orderlines": [{"item": 8, "quantity": 8, "location": 1071, "weight": 1.722}, {"item": 12, "quantity": 10, "location": 2506, "weight": 6.795}]}, {"order_id": 20, "num_orderlines": 1, "total_weight": 1.485, "orderlines": [{"item": 1, "quantity": 3, "location": 313, "weight": 1.485}]}, {"order_id": 21, "num_orderlines": 2, "total_weight": 1.054, "orderlines": [{"item": 67, "quantity": 1, "location": 2517, "weight": 0.374}, {"item": 145, "quantity": 2, "location": 1765, "weight": 0.681}]}, {"order_id": 22, "num_orderlines": 1, "total_weight": 4.455, "orderlines": [{"item": 1, "quantity": 9, "location": 313, "weight": 4.455}]}, {"order_id": 23, "num_orderlines": 1, "total_weight": 1.052, "orderlines": [{"item": 144, "quantity": 2, "location": 688, "weight": 1.052}]}, {"order_id": 24, "num_orderlines": 1, "total_weight": 5.206, "orderlines": [{"item": 236, "quantity": 10, "location": 1773, "weight": 5.206}]}, {"order_id": 25, "num_orderlines": 2, "total_weight": 2.933, "orderlines": [{"item": 78, "quantity": 4, "location": 681, "weight": 2.405}, {"item": 37, "quantity": 1, "location": 2147, "weight": 0.528}]}, {"order_id": 26, "num_orderlines": 2, "total_weight": 5.12, "orderlines": [{"item": 147, "quantity": 2, "location": 2125, "weight": 1.137}, {"item": 0, "quantity": 5, "location": 716, "weight": 3.983}]}, {"order_id": 27, "num_orderlines": 2, "total_weight": 1.041, "orderlines": [{"item": 75, "quantity": 1, "location": 676, "weight": 0.353}, {"item": 124, "quantity": 5, "location": 1065, "weight": 0.688}]}, {"order_id": 28, "num_orderlines": 1, "total_weight": 3.026, "orderlines": [{"item": 106, "quantity": 6, "location": 1035, "weight": 3.026}]}, {"order_id": 29, "num_orderlines": 2, "total_weight": 11.011, "orderlines": [{"item": 0, "quantity": 4, "location": 716, "weight": 3.186}, {"item": 5, "quantity": 8, "location": 1076, "weight": 7.825}]}, {"order_id": 30, "num_orderlines": 1, "total_weight": 2.15, "orderlines": [{"item": 28, "quantity": 9, "location": 1067, "weight": 2.15}]}, {"order_id": 31, "num_orderlines": 1, "total_weight": 1.522, "orderlines": [{"item": 15, "quantity": 5, "location": 1070, "weight": 1.522}]}, {"order_id": 32, "num_orderlines": 2, "total_weight": 2.629, "orderlines": [{"item": 136, "quantity": 1, "location": 705, "weight": 0.963}, {"item": 194, "quantity": 7, "location": 2499, "weight": 1.666}]}, {"order_id": 33, "num_orderlines": 2, "total_weight": 2.076, "orderlines": [{"item": 2, "quantity": 2, "location": 340, "weight": 1.745}, {"item": 172, "quantity": 1, "location": 318, "weight": 0.33}]}, {"order_id": 34, "num_orderlines": 1, "total_weight": 1.517, "orderlines": [{"item": 199, "quantity": 4, "location": 1399, "weight": 1.517}]}, {"order_id": 35, "num_orderlines": 2, "total_weight": 2.94, "orderlines": [{"item": 25, "quantity": 2, "location": 1041, "weight": 0.55}, {"item": 0, "quantity": 3, "location": 716, "weight": 2.39}]}, {"order_id": 36, "num_orderlines": 1, "total_weight": 2.657, "orderlines": [{"item": 93, "quantity": 6, "location": 2876, "weight": 2.657}]}, {"order_id": 37, "num_orderlines": 1, "total_weight": 1.085, "orderlines": [{"item": 36, "quantity": 5, "location": 2500, "weight": 1.085}]}, {"order_id": 38, "num_orderlines": 1, "total_weight": 2.39, "orderlines": [{"item": 0, "quantity": 3, "location": 716, "weight": 2.39}]}, {"order_id": 39, "num_orderlines": 2, "total_weight": 4.041, "orderlines": [{"item": 2, "quantity": 3, "location": 340, "weight": 2.618}, {"item": 90, "quantity": 6, "location": 1074, "weight": 1.423}]}, {"order_id": 40, "num_orderlines": 1, "total_weight": 1.836, "orderlines": [{"item": 57, "quantity": 3, "location": 356, "weight": 1.836}]}, {"order_id": 41, "num_orderlines": 1, "total_weight": 3.794, "orderlines": [{"item": 123, "quantity": 8, "location": 2510, "weight": 3.794}]}, {"order_id": 42, "num_orderlines": 1, "total_weight": 6.28, "orderlines": [{"item": 6, "quantity": 8, "location": 1393, "weight": 6.28}]}, {"order_id": 43, "num_orderlines": 2, "total_weight": 5.55, "orderlines": [{"item": 30, "quantity": 1, "location": 2130, "weight": 0.77}, {"item": 0, "quantity": 6, "location": 716, "weight": 4.78}]}, {"order_id": 44, "num_orderlines": 2, "total_weight": 7.27, "orderlines": [{"item": 7, "quantity": 5, "location": 1408, "weight": 4.037}, {"item": 52, "quantity": 4, "location": 1397, "weight": 3.233}]}, {"order_id": 45, "num_orderlines": 1, "total_weight": 2.934, "orderlines": [{"item": 5, "quantity": 3, "location": 1076, "weight": 2.934}]}, {"order_id": 46, "num_orderlines": 2, "total_weight": 10.251, "orderlines": [{"item": 0, "quantity": 4, "location": 716, "weight": 3.186}, {"item": 6, "quantity": 9, "location": 1393, "weight": 7.065}]}, {"order_id": 47, "num_orderlines": 1, "total_weight": 7.065, "orderlines": [{"item": 6, "quantity": 9, "location": 1393, "weight": 7.065}]}, {"order_id": 48, "num_orderlines": 2, "total_weight": 10.028, "orderlines": [{"item": 155, "quantity": 4, "location": 2514, "weight": 2.82}, {"item": 104, "quantity": 9, "location": 3235, "weight": 7.208}]}, {"order_id": 49, "num_orderlines": 1, "total_weight": 7.204, "orderlines": [{"item": 24, "quantity": 9, "location": 351, "weight": 7.204}]}, {"order_id": 50, "num_orderlines": 1, "total_weight": 7.475, "orderlines": [{"item": 117, "quantity": 10, "location": 2142, "weight": 7.475}]}, {"order_id": 51, "num_orderlines": 1, "total_weight": 0.96, "orderlines": [{"item": 223, "quantity": 1, "location": 2134, "weight": 0.96}]}, {"order_id": 52, "num_orderlines": 1, "total_weight": 5.622, "orderlines": [{"item": 39, "quantity": 8, "location": 1073, "weight": 5.622}]}, {"order_id": 53, "num_orderlines": 2, "total_weight": 6.782, "orderlines": [{"item": 0, "quantity": 6, "location": 716, "weight": 4.78}, {"item": 95, "quantity": 3, "location": 1764, "weight": 2.002}]}, {"order_id": 54, "num_orderlines": 2, "total_weight": 7.934, "orderlines": [{"item": 51, "quantity": 1, "location": 2135, "weight": 0.107}, {"item": 116, "quantity": 10, "location": 3597, "weight": 7.827}]}, {"order_id": 55, "num_orderlines": 2, "total_weight": 3.356, "orderlines": [{"item": 149, "quantity": 7, "location": 2138, "weight": 0.837}, {"item": 50, "quantity": 9, "location": 2137, "weight": 2.519}]}, {"order_id": 56, "num_orderlines": 2, "total_weight": 6.818, "orderlines": [{"item": 14, "quantity": 7, "location": 693, "weight": 3.494}, {"item": 277, "quantity": 6, "location": 1058, "weight": 3.325}]}, {"order_id": 57, "num_orderlines": 1, "total_weight": 0.745, "orderlines": [{"item": 105, "quantity": 1, "location": 2507, "weight": 0.745}]}, {"order_id": 58, "num_orderlines": 1, "total_weight": 2.718, "orderlines": [{"item": 12, "quantity": 4, "location": 2506, "weight": 2.718}]}, {"order_id": 59, "num_orderlines": 1, "total_weight": 1.391, "orderlines": [{"item": 77, "quantity": 2, "location": 702, "weight": 1.391}]}, {"order_id": 60, "num_orderlines": 1, "total_weight": 6.548, "orderlines": [{"item": 3, "quantity": 9, "location": 700, "weight": 6.548}]}, {"order_id": 61, "num_orderlines": 2, "total_weight": 6.231, "orderlines": [{"item": 15, "quantity": 10, "location": 1070, "weight": 3.045}, {"item": 0, "quantity": 4, "location": 716, "weight": 3.186}]}, {"order_id": 62, "num_orderlines": 2, "total_weight": 11.285, "orderlines": [{"item": 364, "quantity": 5, "location": 2468, "weight": 3.461}, {"item": 5, "quantity": 8, "location": 1076, "weight": 7.825}]}, {"order_id": 63, "num_orderlines": 1, "total_weight": 0.795, "orderlines": [{"item": 184, "quantity": 1, "location": 3239, "weight": 0.795}]}, {"order_id": 64, "num_orderlines": 1, "total_weight": 5.108, "orderlines": [{"item": 101, "quantity": 7, "location": 1417, "weight": 5.108}]}, {"order_id": 65, "num_orderlines": 2, "total_weight": 4.15, "orderlines": [{"item": 130, "quantity": 4, "location": 2868, "weight": 1.014}, {"item": 34, "quantity": 6, "location": 1433, "weight": 3.136}]}, {"order_id": 66, "num_orderlines": 2, "total_weight": 2.566, "orderlines": [{"item": 80, "quantity": 1, "location": 1053, "weight": 0.698}, {"item": 11, "quantity": 2, "location": 307, "weight": 1.868}]}, {"order_id": 67, "num_orderlines": 2, "total_weight": 2.426, "orderlines": [{"item": 0, "quantity": 1, "location": 716, "weight": 0.797}, {"item": 85, "quantity": 9, "location": 663, "weight": 1.629}]}, {"order_id": 68, "num_orderlines": 1, "total_weight": 0.623, "orderlines": [{"item": 211, "quantity": 1, "location": 1402, "weight": 0.623}]}, {"order_id": 69, "num_orderlines": 2, "total_weight": 6.218, "orderlines": [{"item": 9, "quantity": 6, "location": 339, "weight": 3.032}, {"item": 0, "quantity": 4, "location": 716, "weight": 3.186}]}, {"order_id": 70, "num_orderlines": 2, "total_weight": 2.857, "orderlines": [{"item": 126, "quantity": 2, "location": 2512, "weight": 0.794}, {"item": 87, "quantity": 4, "location": 2124, "weight": 2.063}]}, {"order_id": 71, "num_orderlines": 2, "total_weight": 6.501, "orderlines": [{"item": 29, "quantity": 4, "location": 718, "weight": 2.859}, {"item": 76, "quantity": 10, "location": 341, "weight": 3.642}]}, {"order_id": 72, "num_orderlines": 1, "total_weight": 1.198, "orderlines": [{"item": 16, "quantity": 2, "location": 1398, "weight": 1.198}]}, {"order_id": 73, "num_orderlines": 2, "total_weight": 5.701, "orderlines": [{"item": 16, "quantity": 3, "location": 1398, "weight": 1.797}, {"item": 10, "quantity": 9, "location": 2148, "weight": 3.903}]}, {"order_id": 74, "num_orderlines": 2, "total_weight": 9.811, "orderlines": [{"item": 129, "quantity": 8, "location": 1428, "weight": 5.031}, {"item": 0, "quantity": 6, "location": 716, "weight": 4.78}]}, {"order_id": 75, "num_orderlines": 1, "total_weight": 3.441, "orderlines": [{"item": 176, "quantity": 7, "location": 673, "weight": 3.441}]}, {"order_id": 76, "num_orderlines": 1, "total_weight": 0.37, "orderlines": [{"item": 4, "quantity": 2, "location": 680, "weight": 0.37}]}, {"order_id": 77, "num_orderlines": 1, "total_weight": 0.835, "orderlines": [{"item": 280, "quantity": 6, "location": 1784, "weight": 0.835}]}, {"order_id": 78, "num_orderlines": 2, "total_weight": 5.239, "orderlines": [{"item": 203, "quantity": 2, "location": 2516, "weight": 0.459}, {"item": 0, "quantity": 6, "location": 716, "weight": 4.78}]}, {"order_id": 79, "num_orderlines": 1, "total_weight": 1.068, "orderlines": [{"item": 137, "quantity": 2, "location": 1438, "weight": 1.068}]}, {"order_id": 80, "num_orderlines": 1, "total_weight": 0.279, "orderlines": [{"item": 27, "quantity": 2, "location": 2519, "weight": 0.279}]}, {"order_id": 81, "num_orderlines": 1, "total_weight": 4.78, "orderlines": [{"item": 0, "quantity": 6, "location": 716, "weight": 4.78}]}, {"order_id": 82, "num_orderlines": 2, "total_weight": 9.325, "orderlines": [{"item": 11, "quantity": 1, "location": 307, "weight": 0.934}, {"item": 225, "quantity": 9, "location": 711, "weight": 8.391}]}, {"order_id": 83, "num_orderlines": 2, "total_weight": 4.93, "orderlines": [{"item": 3, "quantity": 5, "location": 700, "weight": 3.638}, {"item": 8, "quantity": 6, "location": 1071, "weight": 1.292}]}, {"order_id": 84, "num_orderlines": 2, "total_weight": 7.422, "orderlines": [{"item": 13, "quantity": 7, "location": 1795, "weight": 5.883}, {"item": 56, "quantity": 3, "location": 2869, "weight": 1.539}]}, {"order_id": 85, "num_orderlines": 1, "total_weight": 4.999, "orderlines": [{"item": 48, "quantity": 7, "location": 664, "weight": 4.999}]}, {"order_id": 86, "num_orderlines": 1, "total_weight": 0.226, "orderlines": [{"item": 49, "quantity": 1, "location": 1411, "weight": 0.226}]}, {"order_id": 87, "num_orderlines": 2, "total_weight": 2.813, "orderlines": [{"item": 16, "quantity": 3, "location": 1398, "weight": 1.797}, {"item": 59, "quantity": 5, "location": 324, "weight": 1.016}]}, {"order_id": 88, "num_orderlines": 2, "total_weight": 6.244, "orderlines": [{"item": 12, "quantity": 8, "location": 2506, "weight": 5.436}, {"item": 7, "quantity": 1, "location": 1408, "weight": 0.807}]}, {"order_id": 89, "num_orderlines": 1, "total_weight": 0.838, "orderlines": [{"item": 21, "quantity": 2, "location": 2513, "weight": 0.838}]}, {"order_id": 90, "num_orderlines": 2, "total_weight": 6.325, "orderlines": [{"item": 2, "quantity": 6, "location": 340, "weight": 5.236}, {"item": 125, "quantity": 2, "location": 3233, "weight": 1.089}]}, {"order_id": 91, "num_orderlines": 2, "total_weight": 12.619, "orderlines": [{"item": 115, "quantity": 9, "location": 1033, "weight": 7.839}, {"item": 0, "quantity": 6, "location": 716, "weight": 4.78}]}, {"order_id": 92, "num_orderlines": 2, "total_weight": 3.29, "orderlines": [{"item": 262, "quantity": 1, "location": 1395, "weight": 0.379}, {"item": 3, "quantity": 4, "location": 700, "weight": 2.91}]}, {"order_id": 93, "num_orderlines": 1, "total_weight": 5.576, "orderlines": [{"item": 0, "quantity": 7, "location": 716, "weight": 5.576}]}, {"order_id": 94, "num_orderlines": 1, "total_weight": 3.405, "orderlines": [{"item": 96, "quantity": 8, "location": 2501, "weight": 3.405}]}, {"order_id": 95, "num_orderlines": 2, "total_weight": 8.369, "orderlines": [{"item": 0, "quantity": 6, "location": 716, "weight": 4.78}, {"item": 46, "quantity": 8, "location": 2864, "weight": 3.59}]}, {"order_id": 96, "num_orderlines": 1, "total_weight": 7.276, "orderlines": [{"item": 3, "quantity": 10, "location": 700, "weight": 7.276}]}, {"order_id": 97, "num_orderlines": 1, "total_weight": 0.918, "orderlines": [{"item": 100, "quantity": 1, "location": 327, "weight": 0.918}]}, {"order_id": 98, "num_orderlines": 2, "total_weight": 7.828, "orderlines": [{"item": 43, "quantity": 8, "location": 689, "weight": 3.049}, {"item": 0, "quantity": 6, "location": 716, "weight": 4.78}]}, {"order_id": 99, "num_orderlines": 1, "total_weight": 1.894, "orderlines": [{"item": 192, "quantity": 9, "location": 2133, "weight": 1.894}]}, {"order_id": 100, "num_orderlines": 2, "total_weight": 2.355, "orderlines": [{"item": 0, "quantity": 2, "location": 716, "weight": 1.593}, {"item": 43, "quantity": 2, "location": 689, "weight": 0.762}]}, {"order_id": 101, "num_orderlines": 1, "total_weight": 1.911, "orderlines": [{"item": 28, "quantity": 8, "location": 1067, "weight": 1.911}]}, {"order_id": 102, "num_orderlines": 1, "total_weight": 4.338, "orderlines": [{"item": 165, "quantity": 10, "location": 1794, "weight": 4.338}]}, {"order_id": 103, "num_orderlines": 1, "total_weight": 7.298, "orderlines": [{"item": 109, "quantity": 8, "location": 713, "weight": 7.298}]}, {"order_id": 104, "num_orderlines": 1, "total_weight": 2.157, "orderlines": [{"item": 47, "quantity": 6, "location": 2154, "weight": 2.157}]}, {"order_id": 105, "num_orderlines": 2, "total_weight": 9.133, "orderlines": [{"item": 82, "quantity": 10, "location": 302, "weight": 8.326}, {"item": 7, "quantity": 1, "location": 1408, "weight": 0.807}]}, {"order_id": 106, "num_orderlines": 1, "total_weight": 2.995, "orderlines": [{"item": 14, "quantity": 6, "location": 693, "weight": 2.995}]}, {"order_id": 107, "num_orderlines": 2, "total_weight": 1.05, "orderlines": [{"item": 58, "quantity": 2, "location": 675, "weight": 0.452}, {"item": 65, "quantity": 1, "location": 2862, "weight": 0.598}]}, {"order_id": 108, "num_orderlines": 1, "total_weight": 7.23, "orderlines": [{"item": 23, "quantity": 8, "location": 1439, "weight": 7.23}]}, {"order_id": 109, "num_orderlines": 2, "total_weight": 2.662, "orderlines": [{"item": 17, "quantity": 7, "location": 323, "weight": 1.102}, {"item": 26, "quantity": 3, "location": 1040, "weight": 1.56}]}, {"order_id": 110, "num_orderlines": 2, "total_weight": 10.3, "orderlines": [{"item": 2, "quantity": 10, "location": 340, "weight": 8.727}, {"item": 32, "quantity": 4, "location": 701, "weight": 1.573}]}, {"order_id": 111, "num_orderlines": 1, "total_weight": 0.535, "orderlines": [{"item": 163, "quantity": 4, "location": 670, "weight": 0.535}]}, {"order_id": 112, "num_orderlines": 1, "total_weight": 2.91, "orderlines": [{"item": 3, "quantity": 4, "location": 700, "weight": 2.91}]}, {"order_id": 113, "num_orderlines": 1, "total_weight": 3.186, "orderlines": [{"item": 0, "quantity": 4, "location": 716, "weight": 3.186}]}, {"order_id": 114, "num_orderlines": 1, "total_weight": 6.646, "orderlines": [{"item": 119, "quantity": 10, "location": 352, "weight": 6.646}]}, {"order_id": 115, "num_orderlines": 1, "total_weight": 6.54, "orderlines": [{"item": 91, "quantity": 9, "location": 1781, "weight": 6.54}]}, {"order_id": 116, "num_orderlines": 2, "total_weight": 4.769, "orderlines": [{"item": 157, "quantity": 5, "location": 1798, "weight": 3.468}, {"item": 10, "quantity": 3, "location": 2148, "weight": 1.301}]}, {"order_id": 117, "num_orderlines": 1, "total_weight": 8.727, "orderlines": [{"item": 2, "quantity": 10, "location": 340, "weight": 8.727}]}, {"order_id": 118, "num_orderlines": 2, "total_weight": 8.863, "orderlines": [{"item": 54, "quantity": 6, "location": 2159, "weight": 4.408}, {"item": 1, "quantity": 9, "location": 313, "weight": 4.455}]}, {"order_id": 119, "num_orderlines": 1, "total_weight": 0.271, "orderlines": [{"item": 35, "quantity": 1, "location": 301, "weight": 0.271}]}, {"order_id": 120, "num_orderlines": 1, "total_weight": 0.315, "orderlines": [{"item": 17, "quantity": 2, "location": 323, "weight": 0.315}]}, {"order_id": 121, "num_orderlines": 2, "total_weight": 9.987, "orderlines": [{"item": 92, "quantity": 3, "location": 1060, "weight": 1.504}, {"item": 381, "quantity": 9, "location": 2806, "weight": 8.482}]}, {"order_id": 122, "num_orderlines": 1, "total_weight": 7.966, "orderlines": [{"item": 0, "quantity": 10, "location": 716, "weight": 7.966}]}, {"order_id": 123, "num_orderlines": 2, "total_weight": 12.71, "orderlines": [{"item": 0, "quantity": 5, "location": 716, "weight": 3.983}, {"item": 2, "quantity": 10, "location": 340, "weight": 8.727}]}, {"order_id": 124, "num_orderlines": 1, "total_weight": 3.186, "orderlines": [{"item": 0, "quantity": 4, "location": 716, "weight": 3.186}]}, {"order_id": 125, "num_orderlines": 1, "total_weight": 0.185, "orderlines": [{"item": 4, "quantity": 1, "location": 680, "weight": 0.185}]}, {"order_id": 126, "num_orderlines": 1, "total_weight": 2.473, "orderlines": [{"item": 45, "quantity": 3, "location": 325, "weight": 2.473}]}, {"order_id": 127, "num_orderlines": 2, "total_weight": 2.698, "orderlines": [{"item": 174, "quantity": 2, "location": 345, "weight": 0.496}, {"item": 25, "quantity": 8, "location": 1041, "weight": 2.202}]}, {"order_id": 128, "num_orderlines": 1, "total_weight": 4.455, "orderlines": [{"item": 1, "quantity": 9, "location": 313, "weight": 4.455}]}, {"order_id": 129, "num_orderlines": 1, "total_weight": 2.802, "orderlines": [{"item": 11, "quantity": 3, "location": 307, "weight": 2.802}]}, {"order_id": 130, "num_orderlines": 2, "total_weight": 6.748, "orderlines": [{"item": 0, "quantity": 7, "location": 716, "weight": 5.576}, {"item": 229, "quantity": 6, "location": 3590, "weight": 1.172}]}, {"order_id": 131, "num_orderlines": 2, "total_weight": 4.328, "orderlines": [{"item": 0, "quantity": 5, "location": 716, "weight": 3.983}, {"item": 107, "quantity": 1, "location": 678, "weight": 0.345}]}, {"order_id": 132, "num_orderlines": 2, "total_weight": 11.036, "orderlines": [{"item": 33, "quantity": 3, "location": 3232, "weight": 1.3}, {"item": 22, "quantity": 10, "location": 1412, "weight": 9.736}]}, {"order_id": 133, "num_orderlines": 1, "total_weight": 1.57, "orderlines": [{"item": 6, "quantity": 2, "location": 1393, "weight": 1.57}]}, {"order_id": 134, "num_orderlines": 2, "total_weight": 3.349, "orderlines": [{"item": 3, "quantity": 2, "location": 700, "weight": 1.455}, {"item": 35, "quantity": 7, "location": 301, "weight": 1.894}]}, {"order_id": 135, "num_orderlines": 2, "total_weight": 7.971, "orderlines": [{"item": 1, "quantity": 4, "location": 313, "weight": 1.98}, {"item": 16, "quantity": 10, "location": 1398, "weight": 5.991}]}, {"order_id": 136, "num_orderlines": 2, "total_weight": 8.457, "orderlines": [{"item": 18, "quantity": 6, "location": 2498, "weight": 5.069}, {"item": 166, "quantity": 4, "location": 692, "weight": 3.387}]}, {"order_id": 137, "num_orderlines": 2, "total_weight": 6.045, "orderlines": [{"item": 29, "quantity": 4, "location": 718, "weight": 2.859}, {"item": 0, "quantity": 4, "location": 716, "weight": 3.186}]}, {"order_id": 138, "num_orderlines": 2, "total_weight": 3.986, "orderlines": [{"item": 138, "quantity": 3, "location": 3230, "weight": 2.413}, {"item": 61, "quantity": 3, "location": 333, "weight": 1.572}]}, {"order_id": 139, "num_orderlines": 1, "total_weight": 5.652, "orderlines": [{"item": 7, "quantity": 7, "location": 1408, "weight": 5.652}]}, {"order_id": 140, "num_orderlines": 2, "total_weight": 14.07, "orderlines": [{"item": 0, "quantity": 7, "location": 716, "weight": 5.576}, {"item": 41, "quantity": 10, "location": 2867, "weight": 8.494}]}, {"order_id": 141, "num_orderlines": 2, "total_weight": 5.096, "orderlines": [{"item": 37, "quantity": 7, "location": 2147, "weight": 3.697}, {"item": 212, "quantity": 5, "location": 1055, "weight": 1.399}]}, {"order_id": 142, "num_orderlines": 1, "total_weight": 4.934, "orderlines": [{"item": 40, "quantity": 10, "location": 2875, "weight": 4.934}]}, {"order_id": 143, "num_orderlines": 2, "total_weight": 12.281, "orderlines": [{"item": 46, "quantity": 8, "location": 2864, "weight": 3.59}, {"item": 99, "quantity": 9, "location": 2497, "weight": 8.691}]}, {"order_id": 144, "num_orderlines": 2, "total_weight": 10.681, "orderlines": [{"item": 20, "quantity": 8, "location": 2874, "weight": 6.258}, {"item": 134, "quantity": 7, "location": 2155, "weight": 4.423}]}, {"order_id": 145, "num_orderlines": 2, "total_weight": 9.217, "orderlines": [{"item": 69, "quantity": 9, "location": 699, "weight": 4.437}, {"item": 0, "quantity": 6, "location": 716, "weight": 4.78}]}, {"order_id": 146, "num_orderlines": 2, "total_weight": 5.882, "orderlines": [{"item": 2, "quantity": 6, "location": 340, "weight": 5.236}, {"item": 8, "quantity": 3, "location": 1071, "weight": 0.646}]}, {"order_id": 147, "num_orderlines": 1, "total_weight": 3.129, "orderlines": [{"item": 20, "quantity": 4, "location": 2874, "weight": 3.129}]}, {"order_id": 148, "num_orderlines": 1, "total_weight": 1.255, "orderlines": [{"item": 27, "quantity": 9, "location": 2519, "weight": 1.255}]}, {"order_id": 149, "num_orderlines": 2, "total_weight": 12.726, "orderlines": [{"item": 11, "quantity": 5, "location": 307, "weight": 4.671}, {"item": 79, "quantity": 10, "location": 1793, "weight": 8.055}]}, {"order_id": 150, "num_orderlines": 2, "total_weight": 2.468, "orderlines": [{"item": 0, "quantity": 2, "location": 716, "weight": 1.593}, {"item": 206, "quantity": 4, "location": 671, "weight": 0.874}]}, {"order_id": 151, "num_orderlines": 2, "total_weight": 4.789, "orderlines": [{"item": 98, "quantity": 9, "location": 308, "weight": 1.856}, {"item": 118, "quantity": 6, "location": 3594, "weight": 2.933}]}, {"order_id": 152, "num_orderlines": 1, "total_weight": 2.475, "orderlines": [{"item": 1, "quantity": 5, "location": 313, "weight": 2.475}]}, {"order_id": 153, "num_orderlines": 1, "total_weight": 4.209, "orderlines": [{"item": 71, "quantity": 9, "location": 1776, "weight": 4.209}]}, {"order_id": 154, "num_orderlines": 1, "total_weight": 2.09, "orderlines": [{"item": 195, "quantity": 8, "location": 1078, "weight": 2.09}]}, {"order_id": 155, "num_orderlines": 2, "total_weight": 4.762, "orderlines": [{"item": 50, "quantity": 7, "location": 2137, "weight": 1.959}, {"item": 11, "quantity": 3, "location": 307, "weight": 2.802}]}, {"order_id": 156, "num_orderlines": 1, "total_weight": 1.593, "orderlines": [{"item": 0, "quantity": 2, "location": 716, "weight": 1.593}]}, {"order_id": 157, "num_orderlines": 2, "total_weight": 4.258, "orderlines": [{"item": 70, "quantity": 7, "location": 1429, "weight": 2.052}, {"item": 88, "quantity": 9, "location": 687, "weight": 2.206}]}, {"order_id": 158, "num_orderlines": 2, "total_weight": 6.881, "orderlines": [{"item": 7, "quantity": 4, "location": 1408, "weight": 3.23}, {"item": 42, "quantity": 5, "location": 1774, "weight": 3.651}]}, {"order_id": 159, "num_orderlines": 2, "total_weight": 5.858, "orderlines": [{"item": 73, "quantity": 10, "location": 3598, "weight": 3.105}, {"item": 202, "quantity": 5, "location": 3596, "weight": 2.753}]}, {"order_id": 160, "num_orderlines": 1, "total_weight": 3.72, "orderlines": [{"item": 214, "quantity": 5, "location": 1394, "weight": 3.72}]}, {"order_id": 161, "num_orderlines": 2, "total_weight": 6.586, "orderlines": [{"item": 193, "quantity": 2, "location": 1046, "weight": 1.696}, {"item": 5, "quantity": 5, "location": 1076, "weight": 4.89}]}, {"order_id": 162, "num_orderlines": 2, "total_weight": 2.538, "orderlines": [{"item": 3, "quantity": 2, "location": 700, "weight": 1.455}, {"item": 141, "quantity": 2, "location": 1401, "weight": 1.083}]}, {"order_id": 163, "num_orderlines": 1, "total_weight": 0.797, "orderlines": [{"item": 0, "quantity": 1, "location": 716, "weight": 0.797}]}, {"order_id": 164, "num_orderlines": 1, "total_weight": 1.869, "orderlines": [{"item": 132, "quantity": 3, "location": 1410, "weight": 1.869}]}, {"order_id": 165, "num_orderlines": 2, "total_weight": 7.316, "orderlines": [{"item": 190, "quantity": 1, "location": 2146, "weight": 0.943}, {"item": 0, "quantity": 8, "location": 716, "weight": 6.373}]}, {"order_id": 166, "num_orderlines": 2, "total_weight": 11.817, "orderlines": [{"item": 5, "quantity": 7, "location": 1076, "weight": 6.847}, {"item": 113, "quantity": 8, "location": 358, "weight": 4.97}]}, {"order_id": 167, "num_orderlines": 2, "total_weight": 7.866, "orderlines": [{"item": 19, "quantity": 7, "location": 1787, "weight": 4.679}, {"item": 0, "quantity": 4, "location": 716, "weight": 3.186}]}, {"order_id": 168, "num_orderlines": 2, "total_weight": 5.435, "orderlines": [{"item": 15, "quantity": 10, "location": 1070, "weight": 3.045}, {"item": 0, "quantity": 3, "location": 716, "weight": 2.39}]}, {"order_id": 169, "num_orderlines": 2, "total_weight": 12.655, "orderlines": [{"item": 0, "quantity": 6, "location": 716, "weight": 4.78}, {"item": 356, "quantity": 10, "location": 993, "weight": 7.875}]}, {"order_id": 170, "num_orderlines": 1, "total_weight": 0.495, "orderlines": [{"item": 1, "quantity": 1, "location": 313, "weight": 0.495}]}, {"order_id": 171, "num_orderlines": 2, "total_weight": 7.823, "orderlines": [{"item": 1, "quantity": 5, "location": 313, "weight": 2.475}, {"item": 19, "quantity": 8, "location": 1787, "weight": 5.348}]}, {"order_id": 172, "num_orderlines": 2, "total_weight": 3.175, "orderlines": [{"item": 152, "quantity": 10, "location": 1036, "weight": 2.262}, {"item": 38, "quantity": 3, "location": 1434, "weight": 0.913}]}, {"order_id": 173, "num_orderlines": 1, "total_weight": 0.728, "orderlines": [{"item": 3, "quantity": 1, "location": 700, "weight": 0.728}]}, {"order_id": 174, "num_orderlines": 1, "total_weight": 1.04, "orderlines": [{"item": 26, "quantity": 2, "location": 1040, "weight": 1.04}]}, {"order_id": 175, "num_orderlines": 1, "total_weight": 0.958, "orderlines": [{"item": 169, "quantity": 1, "location": 1432, "weight": 0.958}]}, {"order_id": 176, "num_orderlines": 2, "total_weight": 5.961, "orderlines": [{"item": 110, "quantity": 7, "location": 2504, "weight": 3.571}, {"item": 0, "quantity": 3, "location": 716, "weight": 2.39}]}, {"order_id": 177, "num_orderlines": 1, "total_weight": 4.78, "orderlines": [{"item": 0, "quantity": 6, "location": 716, "weight": 4.78}]}]}