{"scenario": 1, "period": 9, "subperiod": 19, "num_orders": 18, "orders": [{"order_id": 0, "num_orderlines": 4, "total_weight": 4.692, "orderlines": [{"item": 4, "quantity": 3, "location": 680, "weight": 0.554}, {"item": 34, "quantity": 5, "location": 1433, "weight": 2.613}, {"item": 3, "quantity": 1, "location": 700, "weight": 0.728}, {"item": 0, "quantity": 1, "location": 716, "weight": 0.797}]}, {"order_id": 1, "num_orderlines": 10, "total_weight": 20.576, "orderlines": [{"item": 35, "quantity": 4, "location": 301, "weight": 1.082}, {"item": 0, "quantity": 3, "location": 716, "weight": 2.39}, {"item": 15, "quantity": 2, "location": 1070, "weight": 0.609}, {"item": 2, "quantity": 4, "location": 340, "weight": 3.491}, {"item": 17, "quantity": 4, "location": 323, "weight": 0.63}, {"item": 25, "quantity": 1, "location": 1041, "weight": 0.275}, {"item": 126, "quantity": 4, "location": 2512, "weight": 1.588}, {"item": 11, "quantity": 1, "location": 307, "weight": 0.934}, {"item": 6, "quantity": 6, "location": 1393, "weight": 4.71}, {"item": 22, "quantity": 5, "location": 1412, "weight": 4.868}]}, {"order_id": 2, "num_orderlines": 10, "total_weight": 14.416, "orderlines": [{"item": 15, "quantity": 6, "location": 1070, "weight": 1.827}, {"item": 0, "quantity": 2, "location": 716, "weight": 1.593}, {"item": 46, "quantity": 1, "location": 2864, "weight": 0.449}, {"item": 7, "quantity": 5, "location": 1408, "weight": 4.037}, {"item": 1, "quantity": 2, "location": 313, "weight": 0.99}, {"item": 28, "quantity": 3, "location": 1067, "weight": 0.717}, {"item": 27, "quantity": 4, "location": 2519, "weight": 0.558}, {"item": 11, "quantity": 2, "location": 307, "weight": 1.868}, {"item": 8, "quantity": 5, "location": 1071, "weight": 1.077}, {"item": 10, "quantity": 3, "location": 2148, "weight": 1.301}]}, {"order_id": 3, "num_orderlines": 3, "total_weight": 3.2, "orderlines": [{"item": 88, "quantity": 5, "location": 687, "weight": 1.226}, {"item": 21, "quantity": 3, "location": 2513, "weight": 1.257}, {"item": 28, "quantity": 3, "location": 1067, "weight": 0.717}]}, {"order_id": 4, "num_orderlines": 7, "total_weight": 17.599, "orderlines": [{"item": 36, "quantity": 6, "location": 2500, "weight": 1.301}, {"item": 7, "quantity": 6, "location": 1408, "weight": 4.845}, {"item": 16, "quantity": 2, "location": 1398, "weight": 1.198}, {"item": 0, "quantity": 4, "location": 716, "weight": 3.186}, {"item": 50, "quantity": 6, "location": 2137, "weight": 1.679}, {"item": 2, "quantity": 6, "location": 340, "weight": 5.236}, {"item": 74, "quantity": 1, "location": 1780, "weight": 0.152}]}, {"order_id": 5, "num_orderlines": 1, "total_weight": 2.183, "orderlines": [{"item": 3, "quantity": 3, "location": 700, "weight": 2.183}]}, {"order_id": 6, "num_orderlines": 5, "total_weight": 13.778, "orderlines": [{"item": 30, "quantity": 5, "location": 2130, "weight": 3.851}, {"item": 12, "quantity": 5, "location": 2506, "weight": 3.397}, {"item": 0, "quantity": 3, "location": 716, "weight": 2.39}, {"item": 19, "quantity": 2, "location": 1787, "weight": 1.337}, {"item": 11, "quantity": 3, "location": 307, "weight": 2.802}]}, {"order_id": 7, "num_orderlines": 5, "total_weight": 10.758, "orderlines": [{"item": 0, "quantity": 1, "location": 716, "weight": 0.797}, {"item": 6, "quantity": 4, "location": 1393, "weight": 3.14}, {"item": 12, "quantity": 4, "location": 2506, "weight": 2.718}, {"item": 1, "quantity": 3, "location": 313, "weight": 1.485}, {"item": 2, "quantity": 3, "location": 340, "weight": 2.618}]}, {"order_id": 8, "num_orderlines": 9, "total_weight": 18.833, "orderlines": [{"item": 3, "quantity": 5, "location": 700, "weight": 3.638}, {"item": 0, "quantity": 6, "location": 716, "weight": 4.78}, {"item": 33, "quantity": 2, "location": 3232, "weight": 0.867}, {"item": 1, "quantity": 5, "location": 313, "weight": 2.475}, {"item": 7, "quantity": 1, "location": 1408, "weight": 0.807}, {"item": 11, "quantity": 5, "location": 307, "weight": 4.671}, {"item": 43, "quantity": 1, "location": 689, "weight": 0.381}, {"item": 18, "quantity": 1, "location": 2498, "weight": 0.845}, {"item": 4, "quantity": 2, "location": 680, "weight": 0.37}]}, {"order_id": 9, "num_orderlines": 10, "total_weight": 28.508, "orderlines": [{"item": 105, "quantity": 6, "location": 2507, "weight": 4.471}, {"item": 54, "quantity": 4, "location": 2159, "weight": 2.938}, {"item": 0, "quantity": 1, "location": 716, "weight": 0.797}, {"item": 5, "quantity": 3, "location": 1076, "weight": 2.934}, {"item": 13, "quantity": 4, "location": 1795, "weight": 3.362}, {"item": 26, "quantity": 5, "location": 1040, "weight": 2.6}, {"item": 65, "quantity": 5, "location": 2862, "weight": 2.991}, {"item": 1, "quantity": 5, "location": 313, "weight": 2.475}, {"item": 2, "quantity": 6, "location": 340, "weight": 5.236}, {"item": 39, "quantity": 1, "location": 1073, "weight": 0.703}]}, {"order_id": 10, "num_orderlines": 3, "total_weight": 10.598, "orderlines": [{"item": 20, "quantity": 6, "location": 2874, "weight": 4.694}, {"item": 0, "quantity": 4, "location": 716, "weight": 3.186}, {"item": 12, "quantity": 4, "location": 2506, "weight": 2.718}]}, {"order_id": 11, "num_orderlines": 10, "total_weight": 15.16, "orderlines": [{"item": 0, "quantity": 1, "location": 716, "weight": 0.797}, {"item": 19, "quantity": 4, "location": 1787, "weight": 2.674}, {"item": 3, "quantity": 1, "location": 700, "weight": 0.728}, {"item": 16, "quantity": 5, "location": 1398, "weight": 2.995}, {"item": 25, "quantity": 2, "location": 1041, "weight": 0.55}, {"item": 67, "quantity": 1, "location": 2517, "weight": 0.374}, {"item": 1, "quantity": 2, "location": 313, "weight": 0.99}, {"item": 31, "quantity": 2, "location": 1403, "weight": 1.942}, {"item": 7, "quantity": 2, "location": 1408, "weight": 1.615}, {"item": 14, "quantity": 5, "location": 693, "weight": 2.495}]}, {"order_id": 12, "num_orderlines": 4, "total_weight": 6.351, "orderlines": [{"item": 5, "quantity": 1, "location": 1076, "weight": 0.978}, {"item": 16, "quantity": 4, "location": 1398, "weight": 2.396}, {"item": 0, "quantity": 1, "location": 716, "weight": 0.797}, {"item": 91, "quantity": 3, "location": 1781, "weight": 2.18}]}, {"order_id": 13, "num_orderlines": 3, "total_weight": 5.046, "orderlines": [{"item": 27, "quantity": 2, "location": 2519, "weight": 0.279}, {"item": 3, "quantity": 5, "location": 700, "weight": 3.638}, {"item": 58, "quantity": 5, "location": 675, "weight": 1.129}]}, {"order_id": 14, "num_orderlines": 6, "total_weight": 9.721, "orderlines": [{"item": 0, "quantity": 2, "location": 716, "weight": 1.593}, {"item": 1, "quantity": 4, "location": 313, "weight": 1.98}, {"item": 15, "quantity": 1, "location": 1070, "weight": 0.304}, {"item": 8, "quantity": 1, "location": 1071, "weight": 0.215}, {"item": 12, "quantity": 4, "location": 2506, "weight": 2.718}, {"item": 3, "quantity": 4, "location": 700, "weight": 2.91}]}, {"order_id": 15, "num_orderlines": 3, "total_weight": 7.844, "orderlines": [{"item": 0, "quantity": 4, "location": 716, "weight": 3.186}, {"item": 3, "quantity": 3, "location": 700, "weight": 2.183}, {"item": 1, "quantity": 5, "location": 313, "weight": 2.475}]}, {"order_id": 16, "num_orderlines": 3, "total_weight": 7.018, "orderlines": [{"item": 0, "quantity": 3, "location": 716, "weight": 2.39}, {"item": 1, "quantity": 2, "location": 313, "weight": 0.99}, {"item": 3, "quantity": 5, "location": 700, "weight": 3.638}]}, {"order_id": 17, "num_orderlines": 1, "total_weight": 4.78, "orderlines": [{"item": 0, "quantity": 6, "location": 716, "weight": 4.78}]}]}